{"trans_result":{"phonetic":[{"src_str":"鸽","trg_str":"gē"},{"src_str":"子","trg_str":"zi"}],"data":[{"result":[[0,"鸽子",["0|4"],[],["0|4"],["0|6"]]],"prefixWrap":0,"dst":"鸽子","src":"dove"}],"from":"en","to":"zh","type":2,"status":0},"dict_result":{"oxford":{"entry":[{"data":[{"data":[{"p":"n","p_text":"noun","tag":"p"},{"data":[{"chText":"鸽子（白鸽常作为和平的象征）","enText":"a bird of the pigeon family. The white dove is often used as a symbol of peace.","tag":"d"},{"chText":"一只鸽子轻柔地咕咕叫。","enText":"A dove cooed softly.","tag":"x"},{"chText":"他穿了一套鸽灰色西装。","enText":"He wore a dove-grey suit.","tag":"x"},{"data":[{"data":[{"canTrans":"1","text":"turtle dove","hoverText":""}],"tag":"xr"}],"tag":"xrs","xt":"see"}],"tag":"n-g","n":"1"},{"data":[{"chText":"鸽派人物，温和派人物（尤指愿意和平与谈判而不愿战争的从政者）","enText":"a person, especially a politician, who prefers peace and discussion to war","tag":"d"},{"data":[{"data":[{"canTrans":"1","text":"hawk","hoverText":""}],"tag":"xr"}],"tag":"xrs","xt":"opp"}],"tag":"n-g","n":"2"}],"tag":"h-g"}],"name":"dove","tag":"entry"},{"data":[{"data":[{"data":[{"data":[{"data":[{"text":"NAmE","hoverText":"北美英语"}],"g":"am","tag":"g"}],"tag":"info"}],"tag":"alone"},{"data":[{"data":[{"canTrans":"","text":"pt","hoverText":"过去式"},{"canTrans":"","text":" of dive","hoverText":""}],"tag":"xr"}],"tag":"xrs","xt":"ptof"}],"tag":"h-g"}],"name":"dove","tag":"entry"}],"unbox":""},"simple_means":{"word_means":["鸽子","鸽派人物，温和派人物","“dive”的过去式"],"from":"original","exchange":{"word_pl":["doves"]},"word_name":"dove","symbols":[{"ph_other":"","parts":[{"means":["鸽子(白鸽常作为和平的象征)","鸽派人物，温和派人物(尤指愿意和平与谈判而不愿战争的从政者)"],"part":"n."},{"means":["“dive”的过去式"],"part":"v."}],"ph_am":"doʊv , dʌv","ph_en":"dəʊv , dʌv"}],"tags":{"core":["CET6","考研"],"other":["TEM8"]}},"synonym":[{"synonyms":[{"ex":[{"chText":"他有两只信鸽。","enText":"He has two carrier pigeons."},{"chText":"那位老人把鸽子作为宠物饲养。","enText":"The old man kept pigeons as pets."}],"bx":"多指体型较大的灰鸽，包括赛鸽、信鸽、菜鸽等。","syn":{"p":"n.","d":["鸽子"],"word":"pigeon"},"tips":""},{"ex":[{"chText":"鸽子常被视为和平的象征。","enText":"The dove is usually regarded as a symbol of peace."},{"chText":"所有的鸽子现在都在咕咕叫。","enText":"All the doves are now cooing."}],"bx":"尤指体型较小的白鸽，常用作和平的象征。","syn":{"p":"n.","d":["鸽子"],"word":"dove"},"tips":""}],"words":["pigeon","dove"],"guide":"导航词义：鸽子"}],"edict":{"item":[{"tr_group":[{"similar_word":[],"tr":["any of numerous small pigeons"],"example":[]},{"similar_word":[],"tr":["an emblem of peace"],"example":[]},{"similar_word":["squab"],"tr":["flesh of a pigeon suitable for roasting or braising","flesh of a dove (young squab) may be broiled"],"example":[]},{"similar_word":["peacenik"],"tr":["someone who prefers negotiations to armed conflict in the conduct of foreign relations"],"example":[]}],"pos":"noun"}],"word":"dove"},"collins":{"entry":[{"type":"boxr","entry_id":"3391","value":[{"boxr_value":"Pronounced /dʌv/ for meanings 1 and 2, and /dəʊv/ for meaning 3. 义项 1 和义项 2 读作 /dʌv/，义项 3 读作 /dəʊv/。"}]},{"type":"mean","entry_id":"3392","value":[{"def":"A <b>dove</b> is a bird that looks like a pigeon but is smaller and lighter in colour. Doves are often used as a symbol of peace.","mean_type":[{"xrsa":[{"xrsa_id":"55","xrsa_see":"turtle dove","posc":[],"defx":[]}],"info_type":"xrsa","info_id":"4759"}],"posp":[{"label":"N-COUNT"}],"gramarinfo":[],"tran":"鸽(常作和平的象征)","mean_id":"3269"}]},{"type":"mean","entry_id":"3393","value":[{"def":"In politics, you can refer to people who support the use of peaceful methods to solve difficult situations as <b>doves</b> .","mean_type":[{"info_type":"example","info_id":"4760","example":[{"tts_mp3":"9/e/0/9e0938a575bddea847703e1e1110c18d.mp3","ex":"A clear split over tactics appears to be emerging between doves and hawks in the party.","example_id":"4661","tran":"党内鸽派和鹰派在策略上似乎将要出现明显的分歧。"}]}],"posp":[{"label":"N-COUNT"}],"gramarinfo":[],"tran":"(政治上的)温和派人物，鸽派","mean_id":"3270"}]},{"type":"mean","entry_id":"3394","value":[{"def":"In American English, <b>dove</b> is sometimes used as the past tense of <b>dive</b>.","mean_type":[],"posp":[],"gramarinfo":[],"tran":"（美国英语中有时用作 dive 的过去式）","mean_id":"3271"}]}],"word_emphasize":"dove","word_id":"1579","word_name":"dove","frequence":"1"},"sanyms":[{"data":[{"p":"n.","d":["pigeon"]}],"type":"synonym","tit":"同义词"}],"baidu_phrase":[{"tit":["turtle dove"],"trans":["斑鸠"]}],"from":"original","lang":"1","queryExplainVideo":{"plays":"0","user_name":"智课网","videoType":"8","query":"dove","duplicate_id":"0","created_at":"2021-01-18 14:45:07","reject_reason":"","type":"0","search_type":"1","coverUrl":"http://media8.smartstudy.com/images/3000ci/dove.jpg","user_pic":"https://fanyiapp.cdn.bcebos.com/cms/oldimage/9358d109b3de9c824de830d66381800a18d843de.jpg","updated_at":"2021-01-18 14:45:08","videoUrl":"http://media6.smartstudy.com/a5/d3/100270/5/dest.mp4?hmsr=25","user_id":"986547206","feed_url":"http://media8.smartstudy.com/images/3000ci/dove.jpg","id":3401,"tag":"讲解","detail":"dove的视频讲解","videoTime":"70","thumbUrl":"https://fanyiapp.cdn.bcebos.com/ugc/image/zhike_dove.jpg","direction":"en_zh","status":"0","likes":"112"}},"logid":2102090340,"liju_result":{"single":"[[[[\"\\\"\",\"w_0\",0],[\"The\",\"w_1\",0,\" \"],[\"dove\",\"w_2\",0,\" \"],[\"is\",\"w_3\",0,\" \"],[\"on\",\"w_4\",0,\" \"],[\"the\",\"w_5\",0,\" \"],[\"window\",\"w_6\",0,\" \"],[\"sill\",\"w_7\",0],[\",\",\"w_8\",0],[\"\\\"\",\"w_9\",0,\" \"],[\"Livni\",\"w_10\",0,\" \"],[\"said\",\"w_11\",0],[\".\",\"w_12\",0]],\"http:\\/\\/www.chinadaily.com.cn\\/world\\/2009-02\\/03\\/content_7440114.htm\"],[[[\"For\",\"w_13\",0,\" \"],[\"mains\",\"w_14\",0],[\",\",\"w_15\",0,\" \"],[\"we\",\"w_16\",0,\" \"],[\"dove\",\"w_17\",0,\" \"],[\"into\",\"w_18\",0,\" \"],[\"a\",\"w_19\",0,\" \"],[\"Mediterranean\",\"w_20\",0,\" \"],[\"dorado\",\"w_21\",0,\" \"],[\"with\",\"w_22\",0,\" \"],[\"lime\",\"w_23\",0,\" \"],[\"sauce\",\"w_24\",0],[\".\",\"w_25\",0]],\"http:\\/\\/www.chinadaily.com.cn\\/citylife\\/2007-07\\/11\\/content_5433070.htm\"],[[[\"The\",\"w_26\",0,\" \"],[\"crowd\",\"w_27\",0,\" \"],[\"cheered\",\"w_28\",0,\" \"],[\"when\",\"w_29\",0,\" \"],[\"a\",\"w_30\",0,\" \"],[\"flock\",\"w_31\",0,\" \"],[\"of\",\"w_32\",0,\" \"],[\"white\",\"w_33\",0,\" \"],[\"doves\",\"w_34\",0,\" \"],[\"was\",\"w_35\",0,\" \"],[\"released\",\"w_36\",0,\" \"],[\"overhead\",\"w_37\",0],[\".\",\"w_38\",0]],\"http:\\/\\/www.chinadaily.com.cn\\/english\\/doc\\/2005-07\\/04\\/content_456728.htm\"],[[[\"One\",\"w_39\",0,\" \"],[\"of\",\"w_40\",0,\" \"],[\"the\",\"w_41\",0,\" \"],[\"female\",\"w_42\",0,\" \"],[\"doves\",\"w_43\",0,\" \"],[\"sat\",\"w_44\",0,\" \"],[\"on\",\"w_45\",0,\" \"],[\"the\",\"w_46\",0,\" \"],[\"eggs\",\"w_47\",0,\" \"],[\"until\",\"w_48\",0,\" \"],[\"they\",\"w_49\",0,\" \"],[\"hatched\",\"w_50\",0],[\".\",\"w_51\",0]],\"http:\\/\\/www.chinadaily.com.cn\\/cndy\\/2007-07\\/21\\/content_5440776.htm\"],[[[\"In\",\"w_52\",0,\" \"],[\"traditional\",\"w_53\",0,\" \"],[\"Chinese\",\"w_54\",0,\" \"],[\"medicine\",\"w_55\",0],[\",\",\"w_56\",0,\" \"],[\"dove\",\"w_57\",0,\" \"],[\"eggs\",\"w_58\",0,\" \"],[\"are\",\"w_59\",0,\" \"],[\"believed\",\"w_60\",0,\" \"],[\"to\",\"w_61\",0,\" \"],[\"have\",\"w_62\",0,\" \"],[\"detoxifying\",\"w_63\",0,\" \"],[\"qualities\",\"w_64\",0],[\".\",\"w_65\",0]],\"http:\\/\\/www.chinadaily.com.cn\\/cndy\\/2011-06\\/18\\/content_12727689.htm\"],[[[\"It\",\"w_66\",0,\" \"],[\"dove\",\"w_67\",0,\" \"],[\"toward\",\"w_68\",0,\" \"],[\"Earth\",\"w_69\",0,\" \"],[\"at\",\"w_70\",0,\" \"],[\"great\",\"w_71\",0,\" \"],[\"speed\",\"w_72\",0],[\",\",\"w_73\",0,\" \"],[\"spinning\",\"w_74\",0,\" \"],[\"rapidly\",\"w_75\",0,\" \"],[\"out\",\"w_76\",0,\" \"],[\"of\",\"w_77\",0,\" \"],[\"control\",\"w_78\",0],[\".\",\"w_79\",0]],\"http:\\/\\/www.chinadaily.com.cn\\/language_tips\\/auvideo\\/2012-10\\/25\\/content_15845568.htm\"],[[[\"The\",\"w_80\",0,\" \"],[\"plan\",\"w_81\",0,\" \"],[\"is\",\"w_82\",0,\" \"],[\"the\",\"w_83\",0,\" \"],[\"brainchild\",\"w_84\",0,\" \"],[\"of\",\"w_85\",0,\" \"],[\"Israeli\",\"w_86\",0,\" \"],[\"opposition\",\"w_87\",0,\" \"],[\"doves\",\"w_88\",0,\" \"],[\"and\",\"w_89\",0,\" \"],[\"some\",\"w_90\",0,\" \"],[\"Palestinian\",\"w_91\",0,\" \"],[\"officials\",\"w_92\",0],[\".\",\"w_93\",0]],\"http:\\/\\/www.chinadaily.com.cn\\/en\\/doc\\/2003-12\\/01\\/content_286164.htm\"],[[[\"He\",\"w_94\",0,\" \"],[\"immediately\",\"w_95\",0,\" \"],[\"scuttled\",\"w_96\",0,\" \"],[\"back\",\"w_97\",0,\" \"],[\"up\",\"w_98\",0,\" \"],[\"the\",\"w_99\",0,\" \"],[\"precipice\",\"w_100\",0,\" \"],[\"and\",\"w_101\",0,\" \"],[\"dove\",\"w_102\",0,\" \"],[\"in\",\"w_103\",0,\" \"],[\"three\",\"w_104\",0,\" \"],[\"more\",\"w_105\",0,\" \"],[\"times\",\"w_106\",0],[\".\",\"w_107\",0]],\"http:\\/\\/www.chinadaily.com.cn\\/china\\/2009-12\\/21\\/content_9205420.htm\"],[[[\"The\",\"w_108\",0,\" \"],[\"song\",\"w_109\",0,\" \"],[\"also\",\"w_110\",0,\" \"],[\"won\",\"w_111\",0,\" \"],[\"a\",\"w_112\",0,\" \"],[\"Dove\",\"w_113\",0,\" \"],[\"Award\",\"w_114\",0,\" \"],[\"from\",\"w_115\",0,\" \"],[\"the\",\"w_116\",0,\" \"],[\"Gospel\",\"w_117\",0,\" \"],[\"Music\",\"w_118\",0,\" \"],[\"Association\",\"w_119\",0,\" \"],[\"last\",\"w_120\",0,\" \"],[\"month\",\"w_121\",0],[\".\",\"w_122\",0]],\"http:\\/\\/www.chinadaily.com.cn\\/entertainment\\/2006-05\\/09\\/content_585638.htm\"],[[[\"Following\",\"w_123\",0,\" \"],[\"the\",\"w_124\",0,\" \"],[\"example\",\"w_125\",0,\" \"],[\"of\",\"w_126\",0,\" \"],[\"his\",\"w_127\",0,\" \"],[\"father\",\"w_128\",0,\" \"],[\"and\",\"w_129\",0,\" \"],[\"grandfather\",\"w_130\",0],[\",\",\"w_131\",0,\" \"],[\"he\",\"w_132\",0,\" \"],[\"dove\",\"w_133\",0,\" \"],[\"into\",\"w_134\",0,\" \"],[\"social\",\"w_135\",0,\" \"],[\"entrepreneurship\",\"w_136\",0],[\".\",\"w_137\",0]],\"http:\\/\\/www.chinadaily.com.cn\\/usa\\/life\\/2012-07\\/17\\/content_15589489.htm\"],[[[\"She\",\"w_138\",0,\" \"],[\"said\",\"w_139\",0,\" \"],[\"church\",\"w_140\",0,\" \"],[\"members\",\"w_141\",0,\" \"],[\"dove\",\"w_142\",0,\" \"],[\"under\",\"w_143\",0,\" \"],[\"church\",\"w_144\",0,\" \"],[\"pews\",\"w_145\",0,\" \"],[\"and\",\"w_146\",0,\" \"],[\"others\",\"w_147\",0,\" \"],[\"ran\",\"w_148\",0,\" \"],[\"out\",\"w_149\",0,\" \"],[\"the\",\"w_150\",0,\" \"],[\"sanctuary\",\"w_151\",0],[\".\",\"w_152\",0]],\"http:\\/\\/www.chinadaily.com.cn\\/world\\/2008-07\\/28\\/content_6880356.htm\"],[[[\"A\",\"w_153\",0,\" \"],[\"woman\",\"w_154\",0,\" \"],[\"in\",\"w_155\",0,\" \"],[\"the\",\"w_156\",0,\" \"],[\"crowed\",\"w_157\",0,\" \"],[\"released\",\"w_158\",0,\" \"],[\"one\",\"w_159\",0,\" \"],[\"white\",\"w_160\",0,\" \"],[\"dove\",\"w_161\",0,\" \"],[\"as\",\"w_162\",0,\" \"],[\"each\",\"w_163\",0,\" \"],[\"acquittal\",\"w_164\",0,\" \"],[\"was\",\"w_165\",0,\" \"],[\"announced\",\"w_166\",0],[\".\",\"w_167\",0]],\"http:\\/\\/www.chinadaily.com.cn\\/english\\/doc\\/2005-06\\/14\\/content_451173.htm\"],[[[\"He\",\"w_168\",0,\" \"],[\"died\",\"w_169\",0,\" \"],[\"as\",\"w_170\",0,\" \"],[\"a\",\"w_171\",0,\" \"],[\"soldier\",\"w_172\",0,\" \"],[\"for\",\"w_173\",0,\" \"],[\"peace\",\"w_174\",0,\" \"],[\"with\",\"w_175\",0,\" \"],[\"a\",\"w_176\",0,\" \"],[\"heart\",\"w_177\",0,\" \"],[\"and\",\"w_178\",0,\" \"],[\"spirit\",\"w_179\",0,\" \"],[\"of\",\"w_180\",0,\" \"],[\"a\",\"w_181\",0,\" \"],[\"dove\",\"w_182\",0],[\".\",\"w_183\",0]],\"http:\\/\\/www.chinadaily.com.cn\\/english\\/doc\\/2005-11\\/05\\/content_491584.htm\"],[[[\"Gao\",\"w_184\",0,\" \"],[\"heard\",\"w_185\",0,\" \"],[\"their\",\"w_186\",0,\" \"],[\"frightened\",\"w_187\",0,\" \"],[\"screams\",\"w_188\",0],[\",\",\"w_189\",0,\" \"],[\"and\",\"w_190\",0,\" \"],[\"dove\",\"w_191\",0,\" \"],[\"into\",\"w_192\",0,\" \"],[\"the\",\"w_193\",0,\" \"],[\"river\",\"w_194\",0,\" \"],[\"to\",\"w_195\",0,\" \"],[\"rescue\",\"w_196\",0,\" \"],[\"the\",\"w_197\",0,\" \"],[\"children\",\"w_198\",0],[\".\",\"w_199\",0]],\"http:\\/\\/www.chinadaily.com.cn\\/cndy\\/2008-06\\/23\\/content_6785183.htm\"],[[[\"Lux\",\"w_200\",0,\" \"],[\"and\",\"w_201\",0,\" \"],[\"Dove\",\"w_202\",0,\" \"],[\"are\",\"w_203\",0,\" \"],[\"owned\",\"w_204\",0,\" \"],[\"by\",\"w_205\",0,\" \"],[\"Unilever\",\"w_206\",0,\" \"],[\"and\",\"w_207\",0,\" \"],[\"are\",\"w_208\",0,\" \"],[\"common\",\"w_209\",0,\" \"],[\"brands\",\"w_210\",0,\" \"],[\"found\",\"w_211\",0,\" \"],[\"on\",\"w_212\",0,\" \"],[\"the\",\"w_213\",0,\" \"],[\"Chinese\",\"w_214\",0,\" \"],[\"mainland\",\"w_215\",0],[\".\",\"w_216\",0]],\"http:\\/\\/www.chinadaily.com.cn\\/business\\/2012-07\\/05\\/content_15552506.htm\"],[[[\"Zeng\",\"w_217\",0,\" \"],[\"got\",\"w_218\",0,\" \"],[\"two\",\"w_219\",0,\" \"],[\"of\",\"w_220\",0,\" \"],[\"the\",\"w_221\",0,\" \"],[\"eggs\",\"w_222\",0,\" \"],[\"and\",\"w_223\",0,\" \"],[\"placed\",\"w_224\",0,\" \"],[\"them\",\"w_225\",0,\" \"],[\"inside\",\"w_226\",0,\" \"],[\"the\",\"w_227\",0,\" \"],[\"nest\",\"w_228\",0,\" \"],[\"of\",\"w_229\",0,\" \"],[\"his\",\"w_230\",0,\" \"],[\"pet\",\"w_231\",0,\" \"],[\"doves\",\"w_232\",0],[\".\",\"w_233\",0]],\"http:\\/\\/www.chinadaily.com.cn\\/cndy\\/2007-07\\/21\\/content_5440776.htm\"],[[[\"Israeli\",\"w_234\",0,\" \"],[\"prime\",\"w_235\",0,\" \"],[\"ministers\",\"w_236\",0,\" \"],[\"have\",\"w_237\",0,\" \"],[\"historically\",\"w_238\",0,\" \"],[\"had\",\"w_239\",0,\" \"],[\"to\",\"w_240\",0,\" \"],[\"govern\",\"w_241\",0,\" \"],[\"a\",\"w_242\",0,\" \"],[\"country\",\"w_243\",0,\" \"],[\"evenly\",\"w_244\",0,\" \"],[\"divided\",\"w_245\",0,\" \"],[\"between\",\"w_246\",0,\" \"],[\"hawks\",\"w_247\",0,\" \"],[\"and\",\"w_248\",0,\" \"],[\"doves\",\"w_249\",0],[\".\",\"w_250\",0]],\"http:\\/\\/www.chinadaily.com.cn\\/cndy\\/2007-01\\/22\\/content_788562.htm\"],[[[\"The\",\"w_251\",0,\" \"],[\"tree\",\"w_252\",0,\" \"],[\"features\",\"w_253\",0,\" \"],[\"moving\",\"w_254\",0,\" \"],[\"images\",\"w_255\",0,\" \"],[\"of\",\"w_256\",0,\" \"],[\"church\",\"w_257\",0,\" \"],[\"bells\",\"w_258\",0,\" \"],[\"and\",\"w_259\",0,\" \"],[\"doves\",\"w_260\",0,\" \"],[\"flickering\",\"w_261\",0,\" \"],[\"from\",\"w_262\",0,\" \"],[\"nearly\",\"w_263\",0,\" \"],[\"3\",\"w_264\",0,\" \"],[\"million\",\"w_265\",0,\" \"],[\"lights\",\"w_266\",0],[\".\",\"w_267\",0]],\"http:\\/\\/www.chinadaily.com.cn\\/english\\/doc\\/2004-12\\/06\\/content_397625.htm\"],[[[\"Church\",\"w_268\",0,\" \"],[\"members\",\"w_269\",0,\" \"],[\"said\",\"w_270\",0,\" \"],[\"they\",\"w_271\",0,\" \"],[\"dove\",\"w_272\",0,\" \"],[\"under\",\"w_273\",0,\" \"],[\"pews\",\"w_274\",0,\" \"],[\"or\",\"w_275\",0,\" \"],[\"ran\",\"w_276\",0,\" \"],[\"from\",\"w_277\",0,\" \"],[\"the\",\"w_278\",0,\" \"],[\"building\",\"w_279\",0,\" \"],[\"when\",\"w_280\",0,\" \"],[\"the\",\"w_281\",0,\" \"],[\"shooting\",\"w_282\",0,\" \"],[\"started\",\"w_283\",0],[\".\",\"w_284\",0]],\"http:\\/\\/www.chinadaily.com.cn\\/world\\/2008-07\\/28\\/content_6881074.htm\"],[[[\"Chen\",\"w_285\",0,\" \"],[\"presented\",\"w_286\",0,\" \"],[\"as\",\"w_287\",0,\" \"],[\"gifts\",\"w_288\",0,\" \"],[\"Davidia\",\"w_289\",0,\" \"],[\"involucrate\",\"w_290\",0,\" \"],[\"seedlings\",\"w_291\",0],[\",\",\"w_292\",0,\" \"],[\"or\",\"w_293\",0,\" \"],[\"\\\"\",\"w_294\",0],[\"dove\",\"w_295\",0,\" \"],[\"tree\",\"w_296\",0],[\"\\\"\",\"w_297\",0,\" \"],[\"as\",\"w_298\",0,\" \"],[\"is\",\"w_299\",0,\" \"],[\"known\",\"w_300\",0,\" \"],[\"here\",\"w_301\",0],[\".\",\"w_302\",0]],\"http:\\/\\/www.chinadaily.com.cn\\/cndy\\/2008-11\\/08\\/content_7186366.htm\"],[[[\"Because\",\"w_303\",0,\" \"],[\"groups\",\"w_304\",0,\" \"],[\"of\",\"w_305\",0,\" \"],[\"doves\",\"w_306\",0,\" \"],[\"nest\",\"w_307\",0,\" \"],[\"in\",\"w_308\",0,\" \"],[\"the\",\"w_309\",0,\" \"],[\"cracks\",\"w_310\",0,\" \"],[\"there\",\"w_311\",0],[\",\",\"w_312\",0,\" \"],[\"it\",\"w_313\",0,\" \"],[\"is\",\"w_314\",0,\" \"],[\"also\",\"w_315\",0,\" \"],[\"called\",\"w_316\",0,\" \"],[\"Dove\",\"w_317\",0,\" \"],[\"Nest\",\"w_318\",0,\" \"],[\"Park\",\"w_319\",0],[\".\",\"w_320\",0]],\"http:\\/\\/www.chinadaily.com.cn\\/m\\/hebei\\/travel\\/2011-05\\/10\\/content_12483554.htm\"],[[[\"As\",\"w_321\",0,\" \"],[\"the\",\"w_322\",0,\" \"],[\"cage\",\"w_323\",0,\" \"],[\"went\",\"w_324\",0,\" \"],[\"up\",\"w_325\",0,\" \"],[\"towards\",\"w_326\",0,\" \"],[\"the\",\"w_327\",0,\" \"],[\"building\",\"w_328\",0],[\"'s\",\"w_329\",0,\" \"],[\"top\",\"w_330\",0],[\",\",\"w_331\",0,\" \"],[\"a\",\"w_332\",0,\" \"],[\"flock\",\"w_333\",0,\" \"],[\"of\",\"w_334\",0,\" \"],[\"doves\",\"w_335\",0,\" \"],[\"flew\",\"w_336\",0,\" \"],[\"overhead\",\"w_337\",0],[\".\",\"w_338\",0]],\"http:\\/\\/www.chinadaily.com.cn\\/en\\/doc\\/2002-07\\/05\\/content_126626.htm\"],[[[\"In\",\"w_339\",0,\" \"],[\"one\",\"w_340\",0,\" \"],[\"photo\",\"w_341\",0],[\",\",\"w_342\",0,\" \"],[\"Zhang\",\"w_343\",0,\" \"],[\"lies\",\"w_344\",0,\" \"],[\"on\",\"w_345\",0,\" \"],[\"his\",\"w_346\",0,\" \"],[\"stomach\",\"w_347\",0,\" \"],[\"as\",\"w_348\",0,\" \"],[\"doves\",\"w_349\",0,\" \"],[\"perch\",\"w_350\",0,\" \"],[\"on\",\"w_351\",0,\" \"],[\"his\",\"w_352\",0,\" \"],[\"back\",\"w_353\",0,\" \"],[\"and\",\"w_354\",0,\" \"],[\"buttocks\",\"w_355\",0],[\".\",\"w_356\",0]],\"http:\\/\\/www.chinadaily.com.cn\\/english\\/doc\\/2005-09\\/29\\/content_481884.htm\"],[[[\"Kate\",\"w_357\",0,\" \"],[\"Moss\",\"w_358\",0,\" \"],[\"was\",\"w_359\",0,\" \"],[\"recently\",\"w_360\",0,\" \"],[\"driven\",\"w_361\",0,\" \"],[\"to\",\"w_362\",0,\" \"],[\"despair\",\"w_363\",0,\" \"],[\"after\",\"w_364\",0,\" \"],[\"her\",\"w_365\",0,\" \"],[\"home\",\"w_366\",0,\" \"],[\"was\",\"w_367\",0,\" \"],[\"invaded\",\"w_368\",0,\" \"],[\"by\",\"w_369\",0,\" \"],[\"a\",\"w_370\",0,\" \"],[\"neighbour\",\"w_371\",0],[\"'s\",\"w_372\",0,\" \"],[\"doves\",\"w_373\",0],[\".\",\"w_374\",0]],\"http:\\/\\/www.chinadaily.com.cn\\/life\\/2009-05\\/28\\/content_7950542.htm\"],[[[\"\\\"\",\"w_375\",0],[\"All\",\"w_376\",0,\" \"],[\"my\",\"w_377\",0,\" \"],[\"doves\",\"w_378\",0,\" \"],[\"get\",\"w_379\",0,\" \"],[\"along\",\"w_380\",0,\" \"],[\"with\",\"w_381\",0,\" \"],[\"the\",\"w_382\",0,\" \"],[\"young\",\"w_383\",0,\" \"],[\"peafowl\",\"w_384\",0,\" \"],[\"like\",\"w_385\",0,\" \"],[\"a\",\"w_386\",0,\" \"],[\"big\",\"w_387\",0,\" \"],[\"family\",\"w_388\",0],[\"\\\"\",\"w_389\",0,\" \"],[\"Zeng\",\"w_390\",0,\" \"],[\"said\",\"w_391\",0],[\".\",\"w_392\",0]],\"http:\\/\\/www.chinadaily.com.cn\\/cndy\\/2007-07\\/21\\/content_5440776.htm\"],[[[\"It\",\"w_393\",0,\" \"],[\"should\",\"w_394\",0,\" \"],[\"not\",\"w_395\",0,\" \"],[\"necessarily\",\"w_396\",0,\" \"],[\"mean\",\"w_397\",0,\" \"],[\"Sharon\",\"w_398\",0],[\"'s\",\"w_399\",0,\" \"],[\"political\",\"w_400\",0,\" \"],[\"journey\",\"w_401\",0,\" \"],[\"is\",\"w_402\",0,\" \"],[\"a\",\"w_403\",0,\" \"],[\"linear\",\"w_404\",0,\" \"],[\"progression\",\"w_405\",0,\" \"],[\"from\",\"w_406\",0,\" \"],[\"hawk\",\"w_407\",0,\" \"],[\"to\",\"w_408\",0,\" \"],[\"dove\",\"w_409\",0],[\".\",\"w_410\",0]],\"http:\\/\\/www.chinadaily.com.cn\\/english\\/doc\\/2006-01\\/09\\/content_510493.htm\"],[[[\"Instead\",\"w_411\",0],[\",\",\"w_412\",0,\" \"],[\"he\",\"w_413\",0,\" \"],[\"fretted\",\"w_414\",0,\" \"],[\"about\",\"w_415\",0,\" \"],[\"the\",\"w_416\",0,\" \"],[\"impact\",\"w_417\",0,\" \"],[\"the\",\"w_418\",0,\" \"],[\"doves\",\"w_419\",0,\" \"],[\"might\",\"w_420\",0,\" \"],[\"have\",\"w_421\",0,\" \"],[\"on\",\"w_422\",0,\" \"],[\"the\",\"w_423\",0,\" \"],[\"freshly\",\"w_424\",0,\" \"],[\"cleaned\",\"w_425\",0,\" \"],[\"window\",\"w_426\",0,\" \"],[\"panes\",\"w_427\",0],[\"!\",\"w_428\",0]],\"http:\\/\\/www.chinadaily.com.cn\\/en\\/doc\\/2002-07\\/05\\/content_126626.htm\"],[[[\"Sato\",\"w_429\",0,\" \"],[\"made\",\"w_430\",0,\" \"],[\"his\",\"w_431\",0,\" \"],[\"only\",\"w_432\",0,\" \"],[\"mistake\",\"w_433\",0,\" \"],[\"of\",\"w_434\",0,\" \"],[\"the\",\"w_435\",0,\" \"],[\"day\",\"w_436\",0,\" \"],[\"as\",\"w_437\",0,\" \"],[\"he\",\"w_438\",0,\" \"],[\"dove\",\"w_439\",0,\" \"],[\"down\",\"w_440\",0,\" \"],[\"the\",\"w_441\",0,\" \"],[\"inside\",\"w_442\",0,\" \"],[\"into\",\"w_443\",0,\" \"],[\"turn\",\"w_444\",0,\" \"],[\"one\",\"w_445\",0],[\".\",\"w_446\",0]],\"http:\\/\\/www.chinadaily.com.cn\\/english\\/doc\\/2004-05\\/31\\/content_335142.htm\"],[[[\"A\",\"w_447\",0,\" \"],[\"dove\",\"w_448\",0,\" \"],[\"acting\",\"w_449\",0,\" \"],[\"as\",\"w_450\",0,\" \"],[\"a\",\"w_451\",0,\" \"],[\"surrogate\",\"w_452\",0,\" \"],[\"mom\",\"w_453\",0,\" \"],[\"hatched\",\"w_454\",0,\" \"],[\"out\",\"w_455\",0,\" \"],[\"two\",\"w_456\",0,\" \"],[\"peafowl\",\"w_457\",0,\" \"],[\"chicks\",\"w_458\",0,\" \"],[\"last\",\"w_459\",0,\" \"],[\"Saturday\",\"w_460\",0,\" \"],[\"in\",\"w_461\",0,\" \"],[\"Tianjin\",\"w_462\",0,\" \"],[\"Municipality\",\"w_463\",0],[\".\",\"w_464\",0]],\"http:\\/\\/www.chinadaily.com.cn\\/cndy\\/2007-07\\/21\\/content_5440776.htm\"],[[[\"Tian\",\"w_465\",0,\" \"],[\"took\",\"w_466\",0,\" \"],[\"a\",\"w_467\",0,\" \"],[\"flashlight\",\"w_468\",0,\" \"],[\"and\",\"w_469\",0,\" \"],[\"dove\",\"w_470\",0,\" \"],[\"into\",\"w_471\",0,\" \"],[\"the\",\"w_472\",0,\" \"],[\"small\",\"w_473\",0,\" \"],[\"entrance\",\"w_474\",0,\" \"],[\"that\",\"w_475\",0,\" \"],[\"only\",\"w_476\",0,\" \"],[\"allowed\",\"w_477\",0,\" \"],[\"one\",\"w_478\",0,\" \"],[\"person\",\"w_479\",0,\" \"],[\"to\",\"w_480\",0,\" \"],[\"pass\",\"w_481\",0,\" \"],[\"through\",\"w_482\",0],[\".\",\"w_483\",0]],\"http:\\/\\/www.chinadaily.com.cn\\/life\\/2013-01\\/31\\/content_16190717.htm\"]]","double":"[[[[\"The\",\"w_0\",\"w_0,w_10\",0,\" \"],[\"dove\",\"w_1\",\"w_1,w_9\",1,\" \"],[\"is\",\"w_2\",\"w_2\",0,\" \"],[\"a\",\"w_3\",\"w_3\",0,\" \"],[\"universal\",\"w_4\",\"w_4,w_12\",0,\" \"],[\"symbol\",\"w_5\",\"w_5,w_13,w_14\",0,\" \"],[\"of\",\"w_6\",\"w_6\",0,\" \"],[\"peace\",\"w_7\",\"w_7,w_11\",0],[\".\",\"w_8\",\"w_8,w_15\",0]],[[\"\\u9e3d\\u5b50\",\"w_9\",\"w_1,w_9\",0],[\"\\u662f\",\"w_10\",\"w_0,w_10\",0],[\"\\u548c\\u5e73\",\"w_11\",\"w_7,w_11\",0],[\"\\u7684\",\"w_12\",\"w_4,w_12\",0],[\"\\u5171\\u540c\",\"w_13\",\"w_5,w_13,w_14\",0],[\"\\u8c61\\u5f81\",\"w_14\",\"w_5,w_13,w_14\",0],[\"\\u3002\",\"w_15\",\"w_8,w_15\",0]],\"\\u300a\\u725b\\u6d25\\u9ad8\\u9636\\u82f1\\u6c49\\u53cc\\u89e3\\u8bcd\\u5178\\u300b\",\"0\"],[[[\"The\",\"w_16\",\"w_16,w_24\",0,\" \"],[\"dove\",\"w_17\",\"w_17,w_23\",1,\" \"],[\"is\",\"w_18\",\"w_18\",0,\" \"],[\"symbolic\",\"w_19\",\"w_19,w_27\",0,\" \"],[\"of\",\"w_20\",\"w_20,w_26\",0,\" \"],[\"peace\",\"w_21\",\"w_21,w_25\",0],[\".\",\"w_22\",\"w_22,w_28\",0]],[[\"\\u9e3d\\u5b50\",\"w_23\",\"w_17,w_23\",0],[\"\\u662f\",\"w_24\",\"w_16,w_24\",0],[\"\\u548c\\u5e73\",\"w_25\",\"w_21,w_25\",0],[\"\\u7684\",\"w_26\",\"w_20,w_26\",0],[\"\\u8c61\\u5f81\",\"w_27\",\"w_19,w_27\",0],[\"\\u3002\",\"w_28\",\"w_22,w_28\",0]],\"\\u300a\\u725b\\u6d25\\u9ad8\\u9636\\u82f1\\u6c49\\u53cc\\u89e3\\u8bcd\\u5178\\u300b\",\"1\"],[[[\"The\",\"w_29\",\"w_29,w_38\",0,\" \"],[\"dove\",\"w_30\",\"w_30,w_37\",1,\" \"],[\"is\",\"w_31\",\"w_31\",0,\" \"],[\"an\",\"w_32\",\"w_32,w_40\",0,\" \"],[\"emblem\",\"w_33\",\"w_33,w_41\",0,\" \"],[\"of\",\"w_34\",\"w_34\",0,\" \"],[\"peace\",\"w_35\",\"w_35,w_39\",0],[\".\",\"w_36\",\"w_36,w_42\",0]],[[\"\\u9e3d\\u5b50\",\"w_37\",\"w_30,w_37\",0],[\"\\u662f\",\"w_38\",\"w_29,w_38\",0],[\"\\u548c\\u5e73\",\"w_39\",\"w_35,w_39\",0],[\"\\u7684\",\"w_40\",\"w_32,w_40\",0],[\"\\u8c61\\u5f81\",\"w_41\",\"w_33,w_41\",0],[\"\\u3002\",\"w_42\",\"w_36,w_42\",0]],\"\\u300a\\u725b\\u6d25\\u9ad8\\u9636\\u82f1\\u6c49\\u53cc\\u89e3\\u8bcd\\u5178\\u300b\",\"2\"],[[[\"A\",\"w_43\",\"w_43,w_48\",0,\" \"],[\"dove\",\"w_44\",\"w_44,w_49,w_50\",1,\" \"],[\"cooed\",\"w_45\",\"w_45,w_46,w_51,w_52,w_53,w_54\",0,\" \"],[\"softly\",\"w_46\",\"w_45,w_46,w_51,w_52,w_53,w_54\",0],[\".\",\"w_47\",\"w_47,w_55\",0]],[[\"\\u4e00\",\"w_48\",\"w_43,w_48\",0],[\"\\u53ea\",\"w_49\",\"w_44,w_49,w_50\",0],[\"\\u9e3d\\u5b50\",\"w_50\",\"w_44,w_49,w_50\",0],[\"\\u8f7b\\u67d4\",\"w_51\",\"w_45,w_46,w_51,w_52,w_53,w_54\",0],[\"\\u5730\",\"w_52\",\"w_45,w_46,w_51,w_52,w_53,w_54\",0],[\"\\u5495\\u5495\",\"w_53\",\"w_45,w_46,w_51,w_52,w_53,w_54\",0],[\"\\u53eb\",\"w_54\",\"w_45,w_46,w_51,w_52,w_53,w_54\",0],[\"\\u3002\",\"w_55\",\"w_47,w_55\",0]],\"\\u300a\\u725b\\u6d25\\u9ad8\\u9636\\u82f1\\u6c49\\u53cc\\u89e3\\u8bcd\\u5178\\u300b\",\"3\"],[[[\"Both\",\"w_56\",\"w_56,w_57,w_69\",0,\" \"],[\"hawks\",\"w_57\",\"w_56,w_57,w_69\",0,\" \"],[\"and\",\"w_58\",\"w_58,w_70\",0,\" \"],[\"doves\",\"w_59\",\"w_59,w_71,w_72\",1,\" \"],[\"have\",\"w_60\",\"w_60,w_73\",0,\" \"],[\"expanded\",\"w_61\",\"w_61,w_74,w_75\",0,\" \"],[\"their\",\"w_62\",\"w_62,w_77\",0,\" \"],[\"conditions\",\"w_63\",\"w_63,w_80\",0,\" \"],[\"for\",\"w_64\",\"w_64\",0,\" \"],[\"ending\",\"w_65\",\"w_65,w_79\",0,\" \"],[\"the\",\"w_66\",\"w_66\",0,\" \"],[\"war\",\"w_67\",\"w_67\",0],[\".\",\"w_68\",\"w_68,w_81\",0]],[[\"\\u9e70\\u6d3e\",\"w_69\",\"w_56,w_57,w_69\",0],[\"\\u548c\",\"w_70\",\"w_58,w_70\",0],[\"\\u9e3d\",\"w_71\",\"w_59,w_71,w_72\",0],[\"\\u6d3e\",\"w_72\",\"w_59,w_71,w_72\",0],[\"\\u90fd\",\"w_73\",\"w_60,w_73\",0],[\"\\u5145\\u5206\",\"w_74\",\"w_61,w_74,w_75\",0],[\"\\u9610\\u660e\",\"w_75\",\"w_61,w_74,w_75\",0],[\"\\u4e86\",\"w_76\",\"\",0],[\"\\u5404\\u81ea\",\"w_77\",\"w_62,w_77\",0],[\"\\u7684\",\"w_78\",\"\",0],[\"\\u505c\\u6218\",\"w_79\",\"w_65,w_79\",0],[\"\\u6761\\u4ef6\",\"w_80\",\"w_63,w_80\",0],[\"\\u3002\",\"w_81\",\"w_68,w_81\",0]],\"\\u300a\\u67ef\\u6797\\u65af\\u9ad8\\u9636\\u82f1\\u6c49\\u53cc\\u89e3\\u5b66\\u4e60\\u8bcd\\u5178\\u300b\",\"4\"],[[[\"A\",\"w_82\",\"w_82\",0,\" \"],[\"clear\",\"w_83\",\"w_83,w_111\",0,\" \"],[\"split\",\"w_84\",\"w_84,w_85,w_113\",0,\" \"],[\"over\",\"w_85\",\"w_84,w_85,w_113\",0,\" \"],[\"tactics\",\"w_86\",\"w_86,w_105\",0,\" \"],[\"appears\",\"w_87\",\"w_87,w_88,w_89,w_107,w_108,w_109\",0,\" \"],[\"to\",\"w_88\",\"w_87,w_88,w_89,w_107,w_108,w_109\",0,\" \"],[\"be\",\"w_89\",\"w_87,w_88,w_89,w_107,w_108,w_109\",0,\" \"],[\"emerging\",\"w_90\",\"w_90,w_110\",0,\" \"],[\"between\",\"w_91\",\"w_91\",0,\" \"],[\"doves\",\"w_92\",\"w_92,w_100,w_101\",1,\" \"],[\"and\",\"w_93\",\"w_93,w_102\",0,\" \"],[\"hawks\",\"w_94\",\"w_94,w_103\",0,\" \"],[\"in\",\"w_95\",\"w_95,w_104\",0,\" \"],[\"the\",\"w_96\",\"w_96\",0,\" \"],[\"party\",\"w_97\",\"w_97,w_99\",0],[\".\",\"w_98\",\"w_98,w_114\",0]],[[\"\\u515a\\u5185\",\"w_99\",\"w_97,w_99\",0],[\"\\u9e3d\",\"w_100\",\"w_92,w_100,w_101\",0],[\"\\u6d3e\",\"w_101\",\"w_92,w_100,w_101\",0],[\"\\u548c\",\"w_102\",\"w_93,w_102\",0],[\"\\u9e70\\u6d3e\",\"w_103\",\"w_94,w_103\",0],[\"\\u5728\",\"w_104\",\"w_95,w_104\",0],[\"\\u7b56\\u7565\",\"w_105\",\"w_86,w_105\",0],[\"\\u4e0a\",\"w_106\",\"\",0],[\"\\u4f3c\\u4e4e\",\"w_107\",\"w_87,w_88,w_89,w_107,w_108,w_109\",0],[\"\\u5c06\",\"w_108\",\"w_87,w_88,w_89,w_107,w_108,w_109\",0],[\"\\u8981\",\"w_109\",\"w_87,w_88,w_89,w_107,w_108,w_109\",0],[\"\\u51fa\\u73b0\",\"w_110\",\"w_90,w_110\",0],[\"\\u660e\\u663e\",\"w_111\",\"w_83,w_111\",0],[\"\\u7684\",\"w_112\",\"\",0],[\"\\u5206\\u6b67\",\"w_113\",\"w_84,w_85,w_113\",0],[\"\\u3002\",\"w_114\",\"w_98,w_114\",0]],\"\\u300a\\u67ef\\u6797\\u65af\\u9ad8\\u9636\\u82f1\\u6c49\\u53cc\\u89e3\\u5b66\\u4e60\\u8bcd\\u5178\\u300b\",\"5\"],[[[\"The\",\"w_115\",\"w_115,w_116,w_126,w_127\",0,\" \"],[\"dove\",\"w_116\",\"w_115,w_116,w_126,w_127\",1,\" \"],[\"is\",\"w_117\",\"w_117,w_128\",0,\" \"],[\"usually\",\"w_118\",\"w_118\",0,\" \"],[\"regarded\",\"w_119\",\"w_119,w_120,w_121,w_129,w_130\",0,\" \"],[\"as\",\"w_120\",\"w_119,w_120,w_121,w_129,w_130\",0,\" \"],[\"a\",\"w_121\",\"w_119,w_120,w_121,w_129,w_130\",0,\" \"],[\"symbol\",\"w_122\",\"w_122,w_133\",0,\" \"],[\"of\",\"w_123\",\"w_123,w_132\",0,\" \"],[\"peace\",\"w_124\",\"w_124,w_131\",0],[\".\",\"w_125\",\"w_125,w_134\",0]],[[\"\\u9e3d\\u5b50\",\"w_126\",\"w_115,w_116,w_126,w_127\",0],[\"\\u5e38\",\"w_127\",\"w_115,w_116,w_126,w_127\",0],[\"\\u88ab\",\"w_128\",\"w_117,w_128\",0],[\"\\u89c6\",\"w_129\",\"w_119,w_120,w_121,w_129,w_130\",0],[\"\\u4e3a\",\"w_130\",\"w_119,w_120,w_121,w_129,w_130\",0],[\"\\u548c\\u5e73\",\"w_131\",\"w_124,w_131\",0],[\"\\u7684\",\"w_132\",\"w_123,w_132\",0],[\"\\u8c61\\u5f81\",\"w_133\",\"w_122,w_133\",0],[\"\\u3002\",\"w_134\",\"w_125,w_134\",0]],\"\\u300a\\u5916\\u7814\\u793e\\u82f1\\u8bed\\u540c\\u4e49\\u8bcd\\u8fa8\\u6790\\u8bcd\\u5178\\u300b\",\"6\"],[[[\"The\",\"w_135\",\"w_135,w_136,w_145\",0,\" \"],[\"magician\",\"w_136\",\"w_135,w_136,w_145\",0,\" \"],[\"waved\",\"w_137\",\"w_137,w_146\",0,\" \"],[\"his\",\"w_138\",\"w_138,w_147\",0,\" \"],[\"hand\",\"w_139\",\"w_139,w_148\",0,\" \"],[\"and\",\"w_140\",\"w_140,w_150\",0,\" \"],[\"the\",\"w_141\",\"w_141\",0,\" \"],[\"dove\",\"w_142\",\"w_142,w_151\",1,\" \"],[\"vanished\",\"w_143\",\"w_143,w_152,w_153,w_154,w_155,w_156\",0],[\".\",\"w_144\",\"w_144,w_157\",0]],[[\"\\u9b54\\u672f\\u5e08\",\"w_145\",\"w_135,w_136,w_145\",0],[\"\\u6325\",\"w_146\",\"w_137,w_146\",0],[\"\\u4e86\",\"w_147\",\"w_138,w_147\",0],[\"\\u4e00\",\"w_148\",\"w_139,w_148\",0],[\"\\u4e0b\\u624b\",\"w_149\",\"\",0],[\"\\uff0c\",\"w_150\",\"w_140,w_150\",0],[\"\\u9e3d\\u5b50\",\"w_151\",\"w_142,w_151\",0],[\"\\u5c31\",\"w_152\",\"w_143,w_152,w_153,w_154,w_155,w_156\",0],[\"\\u7a81\\u7136\",\"w_153\",\"w_143,w_152,w_153,w_154,w_155,w_156\",0],[\"\\u4e0d\",\"w_154\",\"w_143,w_152,w_153,w_154,w_155,w_156\",0],[\"\\u89c1\",\"w_155\",\"w_143,w_152,w_153,w_154,w_155,w_156\",0],[\"\\u4e86\",\"w_156\",\"w_143,w_152,w_153,w_154,w_155,w_156\",0],[\"\\u3002\",\"w_157\",\"w_144,w_157\",0]],\"\\u300a\\u5916\\u7814\\u793e\\u82f1\\u8bed\\u540c\\u4e49\\u8bcd\\u8fa8\\u6790\\u8bcd\\u5178\\u300b\",\"7\"],[[[\"All\",\"w_158\",\"w_158,w_165\",0,\" \"],[\"the\",\"w_159\",\"w_159,w_166\",0,\" \"],[\"doves\",\"w_160\",\"w_160,w_167\",1,\" \"],[\"are\",\"w_161\",\"w_161,w_169,w_170\",0,\" \"],[\"now\",\"w_162\",\"w_162,w_168\",0,\" \"],[\"cooing\",\"w_163\",\"w_163,w_171,w_172\",0],[\".\",\"w_164\",\"w_164,w_173\",0]],[[\"\\u6240\\u6709\",\"w_165\",\"w_158,w_165\",0],[\"\\u7684\",\"w_166\",\"w_159,w_166\",0],[\"\\u9e3d\\u5b50\",\"w_167\",\"w_160,w_167\",0],[\"\\u73b0\\u5728\",\"w_168\",\"w_162,w_168\",0],[\"\\u90fd\",\"w_169\",\"w_161,w_169,w_170\",0],[\"\\u5728\",\"w_170\",\"w_161,w_169,w_170\",0],[\"\\u5495\\u5495\",\"w_171\",\"w_163,w_171,w_172\",0],[\"\\u53eb\",\"w_172\",\"w_163,w_171,w_172\",0],[\"\\u3002\",\"w_173\",\"w_164,w_173\",0]],\"\\u300a\\u5916\\u7814\\u793e\\u82f1\\u8bed\\u540c\\u4e49\\u8bcd\\u8fa8\\u6790\\u8bcd\\u5178\\u300b\",\"8\"],[[[\"It\",\"w_174\",\"w_174,w_184,w_185\",0],[\"'s\",\"w_175\",\"w_175,w_186\",0,\" \"],[\"a\",\"w_176\",\"w_176\",0,\" \"],[\"good\",\"w_177\",\"w_177,w_191\",0,\" \"],[\"time\",\"w_178\",\"w_178,w_192\",0,\" \"],[\"to\",\"w_179\",\"w_179\",0,\" \"],[\"pair\",\"w_180\",\"w_180,w_188\",0,\" \"],[\"the\",\"w_181\",\"w_181,w_190\",0,\" \"],[\"doves\",\"w_182\",\"w_182,w_187\",1],[\".\",\"w_183\",\"w_183,w_193\",0]],[[\"\\u73b0\\u5728\",\"w_184\",\"w_174,w_184,w_185\",0],[\"\\u6b63\",\"w_185\",\"w_174,w_184,w_185\",0],[\"\\u662f\",\"w_186\",\"w_175,w_186\",0],[\"\\u9e3d\\u5b50\",\"w_187\",\"w_182,w_187\",0],[\"\\u914d\\u5bf9\",\"w_188\",\"w_180,w_188\",0],[\"\\u513f\",\"w_189\",\"\",0],[\"\\u7684\",\"w_190\",\"w_181,w_190\",0],[\"\\u597d\",\"w_191\",\"w_177,w_191\",0],[\"\\u65f6\\u5019\",\"w_192\",\"w_178,w_192\",0],[\"\\u3002\",\"w_193\",\"w_183,w_193\",0]],\"\\u767e\\u5ea6\\u7ffb\\u8bd1\\u4f8b\\u53e5\\u5e93\",\"9\"],[[[\"The\",\"w_194\",\"w_194\",0,\" \"],[\"white\",\"w_195\",\"w_195,w_196,w_206\",0,\" \"],[\"dove\",\"w_196\",\"w_195,w_196,w_206\",1,\" \"],[\"is\",\"w_197\",\"w_197,w_207\",0,\" \"],[\"looked\",\"w_198\",\"w_198,w_199,w_208\",0,\" \"],[\"upon\",\"w_199\",\"w_198,w_199,w_208\",0,\" \"],[\"as\",\"w_200\",\"w_200,w_209\",0,\" \"],[\"the\",\"w_201\",\"w_201,w_211\",0,\" \"],[\"symbol\",\"w_202\",\"w_202,w_212\",0,\" \"],[\"of\",\"w_203\",\"w_203\",0,\" \"],[\"peace\",\"w_204\",\"w_204,w_210\",0],[\".\",\"w_205\",\"w_205,w_213\",0]],[[\"\\u767d\\u9e3d\",\"w_206\",\"w_195,w_196,w_206\",0],[\"\\u88ab\",\"w_207\",\"w_197,w_207\",0],[\"\\u770b\\u6210\",\"w_208\",\"w_198,w_199,w_208\",0],[\"\\u662f\",\"w_209\",\"w_200,w_209\",0],[\"\\u548c\\u5e73\",\"w_210\",\"w_204,w_210\",0],[\"\\u7684\",\"w_211\",\"w_201,w_211\",0],[\"\\u8c61\\u5f81\",\"w_212\",\"w_202,w_212\",0],[\"\\u3002\",\"w_213\",\"w_205,w_213\",0]],\"\\u767e\\u5ea6\\u7ffb\\u8bd1\\u4f8b\\u53e5\\u5e93\",\"10\"],[[[\"Both\",\"w_214\",\"w_214,w_215,w_227\",0,\" \"],[\"hawks\",\"w_215\",\"w_214,w_215,w_227\",0,\" \"],[\"and\",\"w_216\",\"w_216,w_228\",0,\" \"],[\"doves\",\"w_217\",\"w_217,w_229,w_230,w_231\",1,\" \"],[\"had\",\"w_218\",\"w_218,w_232,w_233\",0,\" \"],[\"their\",\"w_219\",\"w_219,w_234\",0,\" \"],[\"say\",\"w_220\",\"w_220,w_235\",0,\" \"],[\"at\",\"w_221\",\"w_221,w_222,w_223,w_225\",0,\" \"],[\"the\",\"w_222\",\"w_221,w_222,w_223,w_225\",0,\" \"],[\"meeting\",\"w_223\",\"w_221,w_222,w_223,w_225\",0],[\".\",\"w_224\",\"w_224,w_238\",0]],[[\"\\u4e0e\\u4f1a\",\"w_225\",\"w_221,w_222,w_223,w_225\",0],[\"\\u7684\",\"w_226\",\"\",0],[\"\\u9e70\\u6d3e\",\"w_227\",\"w_214,w_215,w_227\",0],[\"\\u548c\",\"w_228\",\"w_216,w_228\",0],[\"\\u9e3d\",\"w_229\",\"w_217,w_229,w_230,w_231\",0],[\"\\u6d3e\",\"w_230\",\"w_217,w_229,w_230,w_231\",0],[\"\\u6210\\u5458\",\"w_231\",\"w_217,w_229,w_230,w_231\",0],[\"\\u90fd\",\"w_232\",\"w_218,w_232,w_233\",0],[\"\\u6709\",\"w_233\",\"w_218,w_232,w_233\",0],[\"\\u53d1\\u8868\",\"w_234\",\"w_219,w_234\",0],[\"\\u610f\\u89c1\",\"w_235\",\"w_220,w_235\",0],[\"\\u7684\",\"w_236\",\"\",0],[\"\\u673a\\u4f1a\",\"w_237\",\"\",0],[\"\\u3002\",\"w_238\",\"w_224,w_238\",0]],\"\\u767e\\u5ea6\\u7ffb\\u8bd1\\u4f8b\\u53e5\\u5e93\",\"11\"],[[[\"The\",\"w_239\",\"w_239\",0,\" \"],[\"doves\",\"w_240\",\"w_240,w_244\",1,\" \"],[\"winged\",\"w_241\",\"w_241,w_242,w_245,w_246,w_247\",0,\" \"],[\"skyward\",\"w_242\",\"w_241,w_242,w_245,w_246,w_247\",0],[\".\",\"w_243\",\"w_243,w_248\",0]],[[\"\\u9e3d\\u5b50\",\"w_244\",\"w_240,w_244\",0],[\"\\u5411\",\"w_245\",\"w_241,w_242,w_245,w_246,w_247\",0],[\"\\u7a7a\\u4e2d\",\"w_246\",\"w_241,w_242,w_245,w_246,w_247\",0],[\"\\u98de\\u53bb\",\"w_247\",\"w_241,w_242,w_245,w_246,w_247\",0],[\"\\u3002\",\"w_248\",\"w_243,w_248\",0]],\"\\u767e\\u5ea6\\u7ffb\\u8bd1\\u4f8b\\u53e5\\u5e93\",\"12\"],[[[\"For\",\"w_249\",\"w_249,w_250,w_309\",0,\" \"],[\"example\",\"w_250\",\"w_249,w_250,w_309\",0],[\",\",\"w_251\",\"w_251,w_310\",0,\" \"],[\"it\",\"w_252\",\"w_252,w_253,w_311\",0,\" \"],[\"may\",\"w_253\",\"w_252,w_253,w_311\",0,\" \"],[\"only\",\"w_254\",\"w_254,w_312\",0,\" \"],[\"be\",\"w_255\",\"w_255\",0,\" \"],[\"through\",\"w_256\",\"w_256,w_313\",0,\" \"],[\"repeated\",\"w_257\",\"w_257,w_314\",0,\" \"],[\"experiments\",\"w_258\",\"w_258,w_316\",0],[\",\",\"w_259\",\"w_259,w_317\",0,\" \"],[\"evidence\",\"w_260\",\"w_260,w_319\",0,\" \"],[\"gathering\",\"w_261\",\"w_261,w_318\",0],[\",\",\"w_262\",\"w_262\",0,\" \"],[\"and\",\"w_263\",\"w_263,w_320\",0,\" \"],[\"finally\",\"w_264\",\"w_264,w_322\",0,\" \"],[\"overturning\",\"w_265\",\"w_265,w_323\",0,\" \"],[\"a\",\"w_266\",\"w_266,w_324\",0,\" \"],[\"theory\",\"w_267\",\"w_267,w_326\",0],[\",\",\"w_268\",\"w_268\",0,\" \"],[\"that\",\"w_269\",\"w_269,w_332\",0,\" \"],[\"a\",\"w_270\",\"w_270,w_325\",0,\" \"],[\"baby\",\"w_271\",\"w_271,w_329\",0,\" \"],[\"will\",\"w_272\",\"w_272,w_273,w_330\",0,\" \"],[\"come\",\"w_273\",\"w_272,w_273,w_330\",0,\" \"],[\"to\",\"w_274\",\"w_274\",0,\" \"],[\"accept\",\"w_275\",\"w_275,w_331\",0,\" \"],[\"the\",\"w_276\",\"w_276\",0,\" \"],[\"idea\",\"w_277\",\"w_277,w_334\",0,\" \"],[\"that\",\"w_278\",\"w_278,w_336\",0,\" \"],[\"other\",\"w_279\",\"w_279,w_280,w_338\",0,\" \"],[\"people\",\"w_280\",\"w_279,w_280,w_338\",0,\" \"],[\"can\",\"w_281\",\"w_281,w_339\",0,\" \"],[\"have\",\"w_282\",\"w_282,w_340\",0,\" \"],[\"different\",\"w_283\",\"w_283,w_341\",0,\" \"],[\"views\",\"w_284\",\"w_284,w_343\",0,\" \"],[\"and\",\"w_285\",\"w_285,w_344\",0,\" \"],[\"desires\",\"w_286\",\"w_286,w_345\",0,\" \"],[\"from\",\"w_287\",\"w_287\",0,\" \"],[\"what\",\"w_288\",\"w_288\",0,\" \"],[\"he\",\"w_289\",\"w_289\",0,\" \"],[\"or\",\"w_290\",\"w_290\",0,\" \"],[\"she\",\"w_291\",\"w_291,w_352\",0,\" \"],[\"has\",\"w_292\",\"w_292\",0],[\",\",\"w_293\",\"w_293,w_346\",0,\" \"],[\"for\",\"w_294\",\"w_294,w_295,w_347\",0,\" \"],[\"example\",\"w_295\",\"w_294,w_295,w_347\",0],[\",\",\"w_296\",\"w_296\",0,\" \"],[\"unlike\",\"w_297\",\"w_297\",0,\" \"],[\"the\",\"w_298\",\"w_298\",0,\" \"],[\"child\",\"w_299\",\"w_299,w_350\",0],[\",\",\"w_300\",\"w_300,w_351\",0,\" \"],[\"Mommy\",\"w_301\",\"w_301,w_348\",0,\" \"],[\"actually\",\"w_302\",\"w_302\",0,\" \"],[\"doesn\",\"w_303\",\"w_303,w_304,w_353\",0],[\"'t\",\"w_304\",\"w_303,w_304,w_353\",0,\" \"],[\"like\",\"w_305\",\"w_305,w_354\",0,\" \"],[\"Dove\",\"w_306\",\"w_306,w_355\",1,\" \"],[\"chocolate\",\"w_307\",\"w_307,w_356\",0,\" \"],[\"\\uff0e\",\"w_308\",\"w_308,w_357\",0]],[[\"\\u4f8b\\u5982\",\"w_309\",\"w_249,w_250,w_309\",0],[\"\\uff0c\",\"w_310\",\"w_251,w_310\",0],[\"\\u53ef\\u80fd\",\"w_311\",\"w_252,w_253,w_311\",0],[\"\\u53ea\\u6709\",\"w_312\",\"w_254,w_312\",0],[\"\\u901a\\u8fc7\",\"w_313\",\"w_256,w_313\",0],[\"\\u53cd\\u590d\",\"w_314\",\"w_257,w_314\",0],[\"\\u7684\",\"w_315\",\"\",0],[\"\\u5b9e\\u9a8c\",\"w_316\",\"w_258,w_316\",0],[\"\\u3001\",\"w_317\",\"w_259,w_317\",0],[\"\\u6536\\u96c6\",\"w_318\",\"w_261,w_318\",0],[\"\\u8bc1\\u636e\",\"w_319\",\"w_260,w_319\",0],[\"\\u5e76\",\"w_320\",\"w_263,w_320\",0],[\"\\u5728\",\"w_321\",\"\",0],[\"\\u6700\\u540e\",\"w_322\",\"w_264,w_322\",0],[\"\\u63a8\\u7ffb\",\"w_323\",\"w_265,w_323\",0],[\"\\u4e00\",\"w_324\",\"w_266,w_324\",0],[\"\\u4e2a\",\"w_325\",\"w_270,w_325\",0],[\"\\u7406\\u8bba\",\"w_326\",\"w_267,w_326\",0],[\"\\u65f6\",\"w_327\",\"\",0],[\",\",\"w_328\",\"\",0],[\"\\u5a74\\u513f\",\"w_329\",\"w_271,w_329\",0],[\"\\u624d\\u4f1a\",\"w_330\",\"w_272,w_273,w_330\",0],[\"\\u63a5\\u53d7\",\"w_331\",\"w_275,w_331\",0],[\"\\u8fd9\\u6837\",\"w_332\",\"w_269,w_332\",0],[\"\\u7684\",\"w_333\",\"\",0],[\"\\u60f3\\u6cd5\",\"w_334\",\"w_277,w_334\",0],[\",\",\"w_335\",\"\",0],[\"\\u5373\",\"w_336\",\"w_278,w_336\",0],[\"\\u5176\",\"w_337\",\"\",0],[\"\\u4ed6\\u4eba\",\"w_338\",\"w_279,w_280,w_338\",0],[\"\\u53ef\\u4ee5\",\"w_339\",\"w_281,w_339\",0],[\"\\u6709\",\"w_340\",\"w_282,w_340\",0],[\"\\u4e0d\\u540c\",\"w_341\",\"w_283,w_341\",0],[\"\\u7684\",\"w_342\",\"\",0],[\"\\u89c2\\u70b9\",\"w_343\",\"w_284,w_343\",0],[\"\\u548c\",\"w_344\",\"w_285,w_344\",0],[\"\\u613f\\u671b\",\"w_345\",\"w_286,w_345\",0],[\"\\uff0c\",\"w_346\",\"w_293,w_346\",0],[\"\\u6bd4\\u5982\",\"w_347\",\"w_294,w_295,w_347\",0],[\"\\u5988\\u5988\",\"w_348\",\"w_301,w_348\",0],[\"\\u4e0d\\u662f\",\"w_349\",\"\",0],[\"\\u5c0f\\u5b69\",\"w_350\",\"w_299,w_350\",0],[\"\\uff0c\",\"w_351\",\"w_300,w_351\",0],[\"\\u5979\",\"w_352\",\"w_291,w_352\",0],[\"\\u4e0d\",\"w_353\",\"w_303,w_304,w_353\",0],[\"\\u559c\\u6b22\",\"w_354\",\"w_305,w_354\",0],[\"\\u5fb7\\u8299\",\"w_355\",\"w_306,w_355\",0],[\"\\u5de7\\u514b\\u529b\",\"w_356\",\"w_307,w_356\",0],[\"\\u3002\",\"w_357\",\"w_308,w_357\",0]],\"\\u9ad8\\u8003\\u771f\\u9898- 2016 \\u6d59\\u6c5f \\u9605\\u8bfbC\",\"13\"],[[[\"A\",\"w_358\",\"w_358,w_359,w_369\",0,\" \"],[\"dove\",\"w_359\",\"w_358,w_359,w_369\",1,\" \"],[\"is\",\"w_360\",\"w_360,w_361,w_362,w_370\",0,\" \"],[\"often\",\"w_361\",\"w_360,w_361,w_362,w_370\",0,\" \"],[\"used\",\"w_362\",\"w_360,w_361,w_362,w_370\",0,\" \"],[\"as\",\"w_363\",\"w_363,w_364,w_371\",0,\" \"],[\"a\",\"w_364\",\"w_363,w_364,w_371\",0,\" \"],[\"symbol\",\"w_365\",\"w_365,w_374\",0,\" \"],[\"of\",\"w_366\",\"w_366,w_373\",0,\" \"],[\"peace\",\"w_367\",\"w_367,w_372\",0],[\".\",\"w_368\",\"w_368,w_375\",0]],[[\"\\u9e3d\",\"w_369\",\"w_358,w_359,w_369\",0],[\"\\u5e38\",\"w_370\",\"w_360,w_361,w_362,w_370\",0],[\"\\u4f5c\\u4e3a\",\"w_371\",\"w_363,w_364,w_371\",0],[\"\\u548c\\u5e73\",\"w_372\",\"w_367,w_372\",0],[\"\\u7684\",\"w_373\",\"w_366,w_373\",0],[\"\\u8c61\\u5f81\",\"w_374\",\"w_365,w_374\",0],[\"\\u3002\",\"w_375\",\"w_368,w_375\",0]],\"www.enread.com\",\"14\"],[[[\"Clifford\",\"w_376\",\"w_376,w_387\",0,\" \"],[\"and\",\"w_377\",\"w_377,w_388\",0,\" \"],[\"his\",\"w_378\",\"w_378,w_389\",0,\" \"],[\"team\",\"w_379\",\"w_379,w_390\",0,\" \"],[\"dove\",\"w_380\",\"w_380\",1,\" \"],[\"the\",\"w_381\",\"w_381,w_395,w_396\",0,\" \"],[\"site\",\"w_382\",\"w_382,w_397,w_398\",0,\" \"],[\"back\",\"w_383\",\"w_383,w_391\",0,\" \"],[\"in\",\"w_384\",\"w_384,w_399,w_400\",0,\" \"],[\"2003\",\"w_385\",\"w_385,w_393,w_394\",0],[\".\",\"w_386\",\"w_386,w_402\",0]],[[\"\\u514b\\u5229\\u798f\\u5fb7\",\"w_387\",\"w_376,w_387\",0],[\"\\u548c\",\"w_388\",\"w_377,w_388\",0],[\"\\u4ed6\\u7684\",\"w_389\",\"w_378,w_389\",0],[\"\\u56e2\\u961f\",\"w_390\",\"w_379,w_390\",0],[\"\\u65e9\",\"w_391\",\"w_383,w_391\",0],[\"\\u5728\",\"w_392\",\"\",0],[\"2003\",\"w_393\",\"w_385,w_393,w_394\",0],[\"\\u5e74\",\"w_394\",\"w_385,w_393,w_394\",0],[\"\\u5c31\",\"w_395\",\"w_381,w_395,w_396\",0],[\"\\u5bf9\",\"w_396\",\"w_381,w_395,w_396\",0],[\"\\u8be5\",\"w_397\",\"w_382,w_397,w_398\",0],[\"\\u5730\",\"w_398\",\"w_382,w_397,w_398\",0],[\"\\u8fdb\\u884c\",\"w_399\",\"w_384,w_399,w_400\",0],[\"\\u4e86\",\"w_400\",\"w_384,w_399,w_400\",0],[\"\\u641c\\u7d22\",\"w_401\",\"\",0],[\"\\u3002\",\"w_402\",\"w_386,w_402\",0]],\"www.keke.com\",\"15\"],[[[\"Some\",\"w_403\",\"w_403,w_417\",0,\" \"],[\"time\",\"w_404\",\"w_404\",0,\" \"],[\"ago\",\"w_405\",\"w_405\",0],[\",\",\"w_406\",\"w_406\",0,\" \"],[\"when\",\"w_407\",\"w_407,w_419\",0,\" \"],[\"the\",\"w_408\",\"w_408,w_420\",0,\" \"],[\"leaves\",\"w_409\",\"w_409,w_418\",0,\" \"],[\"filled\",\"w_410\",\"w_410\",0,\" \"],[\"up\",\"w_411\",\"w_411,w_422\",0],[\",\",\"w_412\",\"w_412,w_421\",0,\" \"],[\"doves\",\"w_413\",\"w_413,w_414,w_424\",1,\" \"],[\"were\",\"w_414\",\"w_413,w_414,w_424\",0,\" \"],[\"added\",\"w_415\",\"w_415,w_423\",0],[\".\",\"w_416\",\"w_416,w_425\",0]],[[\"\\u540e\\u6765\",\"w_417\",\"w_403,w_417\",0],[\"\\u53f6\\u5b50\",\"w_418\",\"w_409,w_418\",0],[\"\\u7528\\u5b8c\",\"w_419\",\"w_407,w_419\",0],[\"\\u4e86\",\"w_420\",\"w_408,w_420\",0],[\"\\uff0c\",\"w_421\",\"w_412,w_421\",0],[\"\\u5f00\\u59cb\",\"w_422\",\"w_411,w_422\",0],[\"\\u52a0\\u5165\",\"w_423\",\"w_415,w_423\",0],[\"\\u9e3d\\u5b50\",\"w_424\",\"w_413,w_414,w_424\",0],[\"\\u3002\",\"w_425\",\"w_416,w_425\",0]],\"www.keke.com\",\"16\"],[[[\"White\",\"w_426\",\"w_426,w_439\",0,\" \"],[\"winged\",\"w_427\",\"w_427,w_440\",0,\" \"],[\"doves\",\"w_428\",\"w_428,w_441,w_442\",1,\" \"],[\"are\",\"w_429\",\"w_429\",0,\" \"],[\"among\",\"w_430\",\"w_430\",0,\" \"],[\"the\",\"w_431\",\"w_431,w_432,w_443\",0,\" \"],[\"first\",\"w_432\",\"w_431,w_432,w_443\",0,\" \"],[\"to\",\"w_433\",\"w_433,w_444\",0,\" \"],[\"reach\",\"w_434\",\"w_434,w_445\",0,\" \"],[\"the\",\"w_435\",\"w_435,w_447\",0,\" \"],[\"ripening\",\"w_436\",\"w_436,w_446\",0,\" \"],[\"fruit\",\"w_437\",\"w_437,w_448\",0],[\".\",\"w_438\",\"w_438\",0]],[[\"\\u767d\",\"w_439\",\"w_426,w_439\",0],[\"\\u7fc5\",\"w_440\",\"w_427,w_440\",0],[\"\\u54c0\",\"w_441\",\"w_428,w_441,w_442\",0],[\"\\u9e3d\",\"w_442\",\"w_428,w_441,w_442\",0],[\"\\u7387\\u5148\",\"w_443\",\"w_431,w_432,w_443\",0],[\"\\u8d76\\u6765\",\"w_444\",\"w_433,w_444\",0],[\"\\u4eab\\u7528\",\"w_445\",\"w_434,w_445\",0],[\"\\u6210\\u719f\",\"w_446\",\"w_436,w_446\",0],[\"\\u7684\",\"w_447\",\"w_435,w_447\",0],[\"\\u679c\\u5b9e\",\"w_448\",\"w_437,w_448\",0]],\"www.keke.com\",\"17\"],[[[\"My\",\"w_449\",\"w_449,w_455\",0,\" \"],[\"love\",\"w_450\",\"w_450,w_457\",0,\" \"],[\"is\",\"w_451\",\"w_451,w_456\",0,\" \"],[\"like\",\"w_452\",\"w_452,w_453,w_458\",0,\" \"],[\"a\",\"w_453\",\"w_452,w_453,w_458\",0,\" \"],[\"dove\",\"w_454\",\"w_454,w_459\",1]],[[\"\\u6211\",\"w_455\",\"w_449,w_455\",0],[\"\\u7684\",\"w_456\",\"w_451,w_456\",0],[\"\\u7231\",\"w_457\",\"w_450,w_457\",0],[\"\\u597d\\u6bd4\",\"w_458\",\"w_452,w_453,w_458\",0],[\"\\u4fe1\\u9e3d\",\"w_459\",\"w_454,w_459\",0]],\"www.keke.com\",\"18\"],[[[\"The\",\"w_460\",\"w_460,w_461,w_476\",0,\" \"],[\"internet\",\"w_461\",\"w_460,w_461,w_476\",0,\" \"],[\"So\",\"w_462\",\"w_462,w_478\",0,\" \"],[\"I\",\"w_463\",\"w_463,w_477\",0,\" \"],[\"dove\",\"w_464\",\"w_464,w_479\",1,\" \"],[\"into\",\"w_465\",\"w_465,w_480\",0,\" \"],[\"the\",\"w_466\",\"w_466,w_483\",0,\" \"],[\"internet\",\"w_467\",\"w_467,w_482\",0,\" \"],[\"because\",\"w_468\",\"w_468,w_484\",0,\" \"],[\"I\",\"w_469\",\"w_469,w_485\",0,\" \"],[\"saw\",\"w_470\",\"w_470,w_486,w_487\",0,\" \"],[\"it\",\"w_471\",\"w_471,w_488\",0,\" \"],[\"is\",\"w_472\",\"w_472,w_489\",0,\" \"],[\"this\",\"w_473\",\"w_473,w_490\",0,\" \"],[\"extensible\",\"w_474\",\"w_474,w_491\",0,\" \"],[\"structure\",\"w_475\",\"w_475,w_492\",0]],[[\"\\u4e92\\u8054\\u7f51\",\"w_476\",\"w_460,w_461,w_476\",0],[\"\\u6211\",\"w_477\",\"w_463,w_477\",0],[\"\\u4e8e\\u662f\",\"w_478\",\"w_462,w_478\",0],[\"\\u5168\\u5fc3\",\"w_479\",\"w_464,w_479\",0],[\"\\u6295\\u5165\",\"w_480\",\"w_465,w_480\",0],[\"\\u5230\",\"w_481\",\"\",0],[\"\\u4e92\\u8054\\u7f51\",\"w_482\",\"w_467,w_482\",0],[\"\\u4e2d\",\"w_483\",\"w_466,w_483\",0],[\"\\u56e0\\u4e3a\",\"w_484\",\"w_468,w_484\",0],[\"\\u6211\",\"w_485\",\"w_469,w_485\",0],[\"\\u770b\\u5230\",\"w_486\",\"w_470,w_486,w_487\",0],[\"\\u4e86\",\"w_487\",\"w_470,w_486,w_487\",0],[\"\\u5b83\",\"w_488\",\"w_471,w_488\",0],[\"\\u7684\",\"w_489\",\"w_472,w_489\",0],[\"\\u53ef\",\"w_490\",\"w_473,w_490\",0],[\"\\u6269\\u5c55\",\"w_491\",\"w_474,w_491\",0],[\"\\u7ed3\\u6784\",\"w_492\",\"w_475,w_492\",0]],\"www.keke.com\",\"19\"],[[[\"So\",\"w_493\",\"w_493,w_504\",0,\" \"],[\"they\",\"w_494\",\"w_494,w_505\",0,\" \"],[\"dove\",\"w_495\",\"w_495,w_506\",1,\" \"],[\"into\",\"w_496\",\"w_496,w_507\",0,\" \"],[\"IRS\",\"w_497\",\"w_497,w_515,w_516,w_517\",0,\" \"],[\"data\",\"w_498\",\"w_498,w_509\",0,\" \"],[\"from\",\"w_499\",\"w_499,w_508\",0,\" \"],[\"2006\",\"w_500\",\"w_500,w_510\",0,\" \"],[\"to\",\"w_501\",\"w_501,w_511\",0,\" \"],[\"2012\",\"w_502\",\"w_502,w_512,w_513\",0],[\".\",\"w_503\",\"w_503,w_519\",0]],[[\"\\u56e0\\u6b64\",\"w_504\",\"w_493,w_504\",0],[\"\\u4ed6\\u4eec\",\"w_505\",\"w_494,w_505\",0],[\"\\u67e5\\u9605\",\"w_506\",\"w_495,w_506\",0],[\"\\u4e86\",\"w_507\",\"w_496,w_507\",0],[\"\\u4ece\",\"w_508\",\"w_499,w_508\",0],[\"2006\",\"w_509\",\"w_498,w_509\",0],[\"\\u5e74\",\"w_510\",\"w_500,w_510\",0],[\"\\u5230\",\"w_511\",\"w_501,w_511\",0],[\"12\",\"w_512\",\"w_502,w_512,w_513\",0],[\"\\u5e74\\u95f4\",\"w_513\",\"w_502,w_512,w_513\",0],[\"\\u7684\",\"w_514\",\"\",0],[\"\\u7f8e\\u56fd\",\"w_515\",\"w_497,w_515,w_516,w_517\",0],[\"\\u56fd\\u7a0e\",\"w_516\",\"w_497,w_515,w_516,w_517\",0],[\"\\u5c40\",\"w_517\",\"w_497,w_515,w_516,w_517\",0],[\"\\u6863\\u6848\",\"w_518\",\"\",0],[\"\\u3002\",\"w_519\",\"w_503,w_519\",0]],\"www.keke.com\",\"20\"],[[[\"Doves\",\"w_520\",\"w_520,w_529\",1,\" \"],[\"are\",\"w_521\",\"w_521,w_522,w_530\",0,\" \"],[\"still\",\"w_522\",\"w_521,w_522,w_530\",0,\" \"],[\"flying\",\"w_523\",\"w_523\",0,\" \"],[\"across\",\"w_524\",\"w_524\",0,\" \"],[\"the\",\"w_525\",\"w_525,w_526,w_535\",0,\" \"],[\"same\",\"w_526\",\"w_525,w_526,w_535\",0,\" \"],[\"gloomy\",\"w_527\",\"w_527,w_534\",0,\" \"],[\"sky\",\"w_528\",\"w_528,w_536\",0]],[[\"\\u5929\\u7a7a\",\"w_529\",\"w_520,w_529\",0],[\"\\u4f9d\\u7136\",\"w_530\",\"w_521,w_522,w_530\",0],[\"\\u9634\\u973e\",\"w_531\",\"\",0],[\"\\u4f9d\\u7136\",\"w_532\",\"\",0],[\"\\u6709\",\"w_533\",\"\",0],[\"\\u9e3d\\u5b50\",\"w_534\",\"w_527,w_534\",0],[\"\\u5728\",\"w_535\",\"w_525,w_526,w_535\",0],[\"\\u98de\\u7fd4\",\"w_536\",\"w_528,w_536\",0]],\"www.keke.com\",\"21\"],[[[\"Lift\",\"w_537\",\"w_537,w_538,w_549,w_550\",0,\" \"],[\"me\",\"w_538\",\"w_537,w_538,w_549,w_550\",0,\" \"],[\"like\",\"w_539\",\"w_539,w_548\",0,\" \"],[\"an\",\"w_540\",\"w_540,w_551\",0,\" \"],[\"olive\",\"w_541\",\"w_541,w_553\",0,\" \"],[\"branch\",\"w_542\",\"w_542,w_554\",0,\" \"],[\"and\",\"w_543\",\"w_543,w_560\",0,\" \"],[\"be\",\"w_544\",\"w_544,w_561\",0,\" \"],[\"my\",\"w_545\",\"w_545,w_562,w_563\",0,\" \"],[\"homeward\",\"w_546\",\"w_546,w_564\",0,\" \"],[\"dove\",\"w_547\",\"w_547,w_565\",1]],[[\"\\u50cf\",\"w_548\",\"w_539,w_548\",0],[\"\\u6276\",\"w_549\",\"w_537,w_538,w_549,w_550\",0],[\"\\u8d77\",\"w_550\",\"w_537,w_538,w_549,w_550\",0],[\"\\u4e00\",\"w_551\",\"w_540,w_551\",0],[\"\\u682a\",\"w_552\",\"\",0],[\"\\u6a44\\u6984\",\"w_553\",\"w_541,w_553\",0],[\"\\u679d\",\"w_554\",\"w_542,w_554\",0],[\"\\u4e00\\u6837\",\"w_555\",\"\",0],[\"\\u5c06\",\"w_556\",\"\",0],[\"\\u6211\",\"w_557\",\"\",0],[\"\\u6276\",\"w_558\",\"\",0],[\"\\u8d77\",\"w_559\",\"\",0],[\"\\uff0c\",\"w_560\",\"w_543,w_560\",0],[\"\\u505a\",\"w_561\",\"w_544,w_561\",0],[\"\\u6211\",\"w_562\",\"w_545,w_562,w_563\",0],[\"\\u7684\",\"w_563\",\"w_545,w_562,w_563\",0],[\"\\u5f52\",\"w_564\",\"w_546,w_564\",0],[\"\\u5bb6\\u9e3d\",\"w_565\",\"w_547,w_565\",0]],\"www.keke.com\",\"22\"],[[[\"But\",\"w_566\",\"w_566,w_573\",0,\" \"],[\"the\",\"w_567\",\"w_567,w_575\",0,\" \"],[\"doves\",\"w_568\",\"w_568,w_574\",1,\" \"],[\"see\",\"w_569\",\"w_569\",0,\" \"],[\"things\",\"w_570\",\"w_570,w_571,w_580,w_581,w_582\",0,\" \"],[\"differently\",\"w_571\",\"w_570,w_571,w_580,w_581,w_582\",0],[\".\",\"w_572\",\"w_572,w_583\",0]],[[\"\\u800c\",\"w_573\",\"w_566,w_573\",0],[\"\\u9e3d\",\"w_574\",\"w_568,w_574\",0],[\"\\u6d3e\",\"w_575\",\"w_567,w_575\",0],[\"\\u4eba\\u58eb\",\"w_576\",\"\",0],[\"\\u5374\",\"w_577\",\"\",0],[\"\\u6709\",\"w_578\",\"\",0],[\"\\u7740\",\"w_579\",\"\",0],[\"\\u4e0d\\u540c\",\"w_580\",\"w_570,w_571,w_580,w_581,w_582\",0],[\"\\u7684\",\"w_581\",\"w_570,w_571,w_580,w_581,w_582\",0],[\"\\u770b\\u6cd5\",\"w_582\",\"w_570,w_571,w_580,w_581,w_582\",0],[\"\\u3002\",\"w_583\",\"w_572,w_583\",0]],\"www.keke.com\",\"23\"],[[[\"Put\",\"w_584\",\"w_584\",0,\" \"],[\"crepe\",\"w_585\",\"w_585\",0,\" \"],[\"bows\",\"w_586\",\"w_586\",0,\" \"],[\"round\",\"w_587\",\"w_587\",0,\" \"],[\"the\",\"w_588\",\"w_588\",0,\" \"],[\"white\",\"w_589\",\"w_589,w_597\",0,\" \"],[\"necks\",\"w_590\",\"w_590,w_591,w_592,w_598,w_599,w_600\",0,\" \"],[\"of\",\"w_591\",\"w_590,w_591,w_592,w_598,w_599,w_600\",0,\" \"],[\"the\",\"w_592\",\"w_590,w_591,w_592,w_598,w_599,w_600\",0,\" \"],[\"public\",\"w_593\",\"w_593,w_594,w_601\",0,\" \"],[\"doves\",\"w_594\",\"w_593,w_594,w_601\",1],[\",\",\"w_595\",\"w_595,w_602\",0]],[[\"\\u4e3a\",\"w_596\",\"\",0],[\"\\u767d\\u9e3d\",\"w_597\",\"w_589,w_597\",0],[\"\\u9888\\u95f4\",\"w_598\",\"w_590,w_591,w_592,w_598,w_599,w_600\",0],[\"\\u7cfb\",\"w_599\",\"w_590,w_591,w_592,w_598,w_599,w_600\",0],[\"\\u4e0a\",\"w_600\",\"w_590,w_591,w_592,w_598,w_599,w_600\",0],[\"\\u9ed1\\u7eb1\",\"w_601\",\"w_593,w_594,w_601\",0],[\"\\uff0c\",\"w_602\",\"w_595,w_602\",0]],\"www.enread.com\",\"24\"],[[[\"The\",\"w_603\",\"w_603,w_614\",0,\" \"],[\"dove\",\"w_604\",\"w_604,w_615\",1,\" \"],[\"descending\",\"w_605\",\"w_605,w_617\",0,\" \"],[\"breaks\",\"w_606\",\"w_606,w_618\",0,\" \"],[\"the\",\"w_607\",\"w_607,w_620\",0,\" \"],[\"air\",\"w_608\",\"w_608,w_623\",0,\" \"],[\"with\",\"w_609\",\"w_609,w_616\",0,\" \"],[\"flame\",\"w_610\",\"w_610,w_621,w_622\",0,\" \"],[\"of\",\"w_611\",\"w_611,w_624\",0,\" \"],[\"incandescent\",\"w_612\",\"w_612,w_625,w_626\",0,\" \"],[\"terror\",\"w_613\",\"w_613,w_619\",0]],[[\"\\u9e3d\\u5b50\",\"w_614\",\"w_603,w_614\",0],[\"\\u55b7\\u5410\",\"w_615\",\"w_604,w_615\",0],[\"\\u7740\",\"w_616\",\"w_609,w_616\",0],[\"\\u70bd\\u70c8\",\"w_617\",\"w_605,w_617\",0],[\"\\u7684\",\"w_618\",\"w_606,w_618\",0],[\"\\u6050\\u6016\",\"w_619\",\"w_613,w_619\",0],[\"\\u7684\",\"w_620\",\"w_607,w_620\",0],[\"\\u706b\\u7130\",\"w_621\",\"w_610,w_621,w_622\",0],[\"\\u5212\\u7834\",\"w_622\",\"w_610,w_621,w_622\",0],[\"\\u591c\\u7a7a\",\"w_623\",\"w_608,w_623\",0],[\"\\uff0c\",\"w_624\",\"w_611,w_624\",0],[\"\\u63a0\",\"w_625\",\"w_612,w_625,w_626\",0],[\"\\u98de\",\"w_626\",\"w_612,w_625,w_626\",0],[\"\\u800c\",\"w_627\",\"\",0],[\"\\u4e0b\",\"w_628\",\"\",0]],\"www.keke.com\",\"25\"],[[[\"We\",\"w_629\",\"w_629,w_647\",0,\" \"],[\"all\",\"w_630\",\"w_630,w_648\",0,\" \"],[\"dove\",\"w_631\",\"w_631,w_632,w_646\",1,\" \"],[\"to\",\"w_632\",\"w_631,w_632,w_646\",0,\" \"],[\"the\",\"w_633\",\"w_633,w_650\",0,\" \"],[\"floor\",\"w_634\",\"w_634,w_651,w_652\",0,\" \"],[\"then\",\"w_635\",\"w_635,w_653\",0,\" \"],[\"moved\",\"w_636\",\"w_636,w_637,w_654,w_655\",0,\" \"],[\"toward\",\"w_637\",\"w_636,w_637,w_654,w_655\",0,\" \"],[\"the\",\"w_638\",\"w_638\",0,\" \"],[\"lobby\",\"w_639\",\"w_639,w_656\",0],[\",\",\"w_640\",\"w_640\",0,\" \"],[\"he\",\"w_641\",\"w_641,w_644\",0,\" \"],[\"said\",\"w_642\",\"w_642,w_645\",0],[\".\",\"w_643\",\"w_643,w_657\",0]],[[\"\\u4ed6\",\"w_644\",\"w_641,w_644\",0],[\"\\u8bf4\",\"w_645\",\"w_642,w_645\",0],[\"\\uff0c\",\"w_646\",\"w_631,w_632,w_646\",0],[\"\\u6211\\u4eec\",\"w_647\",\"w_629,w_647\",0],[\"\\u90fd\",\"w_648\",\"w_630,w_648\",0],[\"\\u8db4\",\"w_649\",\"\",0],[\"\\u5728\",\"w_650\",\"w_633,w_650\",0],[\"\\u5730\\u677f\",\"w_651\",\"w_634,w_651,w_652\",0],[\"\\u4e0a\",\"w_652\",\"w_634,w_651,w_652\",0],[\"\\u7136\\u540e\",\"w_653\",\"w_635,w_653\",0],[\"\\u79fb\\u52a8\",\"w_654\",\"w_636,w_637,w_654,w_655\",0],[\"\\u5230\",\"w_655\",\"w_636,w_637,w_654,w_655\",0],[\"\\u5927\\u5385\",\"w_656\",\"w_639,w_656\",0],[\"\\u3002\",\"w_657\",\"w_643,w_657\",0]],\"www.keke.com\",\"26\"],[[[\"You\",\"w_658\",\"w_658,w_669\",0,\" \"],[\"saw\",\"w_659\",\"w_659,w_670\",0,\" \"],[\"it\",\"w_660\",\"w_660,w_668\",0],[\",\",\"w_661\",\"w_661,w_671,w_672\",0,\" \"],[\"but\",\"w_662\",\"w_662,w_673\",0,\" \"],[\"I\",\"w_663\",\"w_663,w_664,w_674\",0,\" \"],[\"dove\",\"w_664\",\"w_663,w_664,w_674\",1,\" \"],[\"for\",\"w_665\",\"w_665,w_666,w_675,w_676\",0,\" \"],[\"it\",\"w_666\",\"w_665,w_666,w_675,w_676\",0],[\".\",\"w_667\",\"w_667,w_677\",0]],[[\"\\u662f\",\"w_668\",\"w_660,w_668\",0],[\"\\u4f60\",\"w_669\",\"w_658,w_669\",0],[\"\\u770b\\u89c1\",\"w_670\",\"w_659,w_670\",0],[\"\\u7684\",\"w_671\",\"w_661,w_671,w_672\",0],[\"\\uff0c\",\"w_672\",\"w_661,w_671,w_672\",0],[\"\\u4f46\",\"w_673\",\"w_662,w_673\",0],[\"\\u6211\",\"w_674\",\"w_663,w_664,w_674\",0],[\"\\u62ff\\u5230\",\"w_675\",\"w_665,w_666,w_675,w_676\",0],[\"\\u7684\",\"w_676\",\"w_665,w_666,w_675,w_676\",0],[\"\\u4e86\",\"w_677\",\"w_667,w_677\",0]],\"www.keke.com\",\"27\"],[[[\"During\",\"w_678\",\"w_678,w_695\",0,\" \"],[\"this\",\"w_679\",\"w_679,w_680,w_696\",0,\" \"],[\"time\",\"w_680\",\"w_679,w_680,w_696\",0],[\",\",\"w_681\",\"w_681,w_700\",0,\" \"],[\"Yang\",\"w_682\",\"w_682,w_701\",0,\" \"],[\"will\",\"w_683\",\"w_683,w_702\",0,\" \"],[\"perform\",\"w_684\",\"w_684,w_703\",0,\" \"],[\"hits\",\"w_685\",\"w_685,w_720,w_721\",0,\" \"],[\"from\",\"w_686\",\"w_686,w_718\",0,\" \"],[\"his\",\"w_687\",\"w_687,w_709\",0,\" \"],[\"three\",\"w_688\",\"w_688,w_715\",0,\" \"],[\"albums\",\"w_689\",\"w_689,w_717\",0,\" \"],[\"including\",\"w_690\",\"w_690,w_712,w_713\",0,\" \"],[\"Dove\",\"w_691\",\"w_691,w_716\",1,\" \"],[\"and\",\"w_692\",\"w_692,w_708\",0,\" \"],[\"Pure\",\"w_693\",\"w_693,w_719\",0],[\".\",\"w_694\",\"w_694\",0]],[[\"\\u5728\",\"w_695\",\"w_678,w_695\",0],[\"\\u8fd9\\u6b21\",\"w_696\",\"w_679,w_680,w_696\",0],[\"\\u6f14\\u5531\",\"w_697\",\"\",0],[\"\\u4f1a\",\"w_698\",\"\",0],[\"\\u671f\\u95f4\",\"w_699\",\"\",0],[\"\\uff0c\",\"w_700\",\"w_681,w_700\",0],[\"\\u6768\\u5b97\\u7eac\",\"w_701\",\"w_682,w_701\",0],[\"\\u5c06\\u4f1a\",\"w_702\",\"w_683,w_702\",0],[\"\\u6f14\\u5531\",\"w_703\",\"w_684,w_703\",0],[\"\\u5305\\u62ec\",\"w_704\",\"\",0],[\"\\u300a\",\"w_705\",\"\",0],[\"\\u9e3d\\u5b50\",\"w_706\",\"\",0],[\"\\u300b\",\"w_707\",\"\",0],[\"\\u548c\",\"w_708\",\"w_692,w_708\",0],[\"\\u300a\",\"w_709\",\"w_687,w_709\",0],[\"\\u539f\\u8272\",\"w_710\",\"\",0],[\"\\u300b\",\"w_711\",\"\",0],[\"\\u7b49\",\"w_712\",\"w_690,w_712,w_713\",0],[\"\\u5728\\u5185\",\"w_713\",\"w_690,w_712,w_713\",0],[\"\\u7684\",\"w_714\",\"\",0],[\"\\u4e09\",\"w_715\",\"w_688,w_715\",0],[\"\\u90e8\",\"w_716\",\"w_691,w_716\",0],[\"\\u4e13\\u8f91\",\"w_717\",\"w_689,w_717\",0],[\"\\u4e2d\",\"w_718\",\"w_686,w_718\",0],[\"\\u7684\",\"w_719\",\"w_693,w_719\",0],[\"\\u70ed\\u95e8\",\"w_720\",\"w_685,w_720,w_721\",0],[\"\\u6b4c\\u66f2\",\"w_721\",\"w_685,w_720,w_721\",0]],\"www.keke.com\",\"28\"],[[[\"It\",\"w_722\",\"w_722,w_723,w_740\",0],[\"'s\",\"w_723\",\"w_722,w_723,w_740\",0,\" \"],[\"a\",\"w_724\",\"w_724,w_742\",0,\" \"],[\"shame.But\",\"w_725\",\"w_725,w_741\",0,\" \"],[\"my\",\"w_726\",\"w_726,w_744\",0,\" \"],[\"brother\",\"w_727\",\"w_727,w_745\",0,\" \"],[\"right\",\"w_728\",\"w_728\",0,\" \"],[\"and\",\"w_729\",\"w_729,w_730,w_746\",0,\" \"],[\"dove\",\"w_730\",\"w_729,w_730,w_746\",1,\" \"],[\"in\",\"w_731\",\"w_731,w_747\",0,\" \"],[\"and\",\"w_732\",\"w_732,w_733,w_748\",0,\" \"],[\"got\",\"w_733\",\"w_732,w_733,w_748\",0,\" \"],[\"me\",\"w_734\",\"w_734,w_749\",0,\" \"],[\"out\",\"w_735\",\"w_735,w_750\",0,\" \"],[\"of\",\"w_736\",\"w_736,w_737,w_751\",0,\" \"],[\"the\",\"w_737\",\"w_736,w_737,w_751\",0,\" \"],[\"pool\",\"w_738\",\"w_738\",0],[\".\",\"w_739\",\"w_739\",0]],[[\"\\u592a\",\"w_740\",\"w_722,w_723,w_740\",0],[\"\\u4e22\\u8138\",\"w_741\",\"w_725,w_741\",0],[\"\\u4e86\",\"w_742\",\"w_724,w_742\",0],[\"\\u597d\\u5728\",\"w_743\",\"\",0],[\"\\u6211\",\"w_744\",\"w_726,w_744\",0],[\"\\u54e5\",\"w_745\",\"w_727,w_745\",0],[\"\\u8df3\\u8fdb\",\"w_746\",\"w_729,w_730,w_746\",0],[\"\\u6cf3\\u6c60\",\"w_747\",\"w_731,w_747\",0],[\"\\u628a\",\"w_748\",\"w_732,w_733,w_748\",0],[\"\\u6211\",\"w_749\",\"w_734,w_749\",0],[\"\\u6551\",\"w_750\",\"w_735,w_750\",0],[\"\\u4e86\",\"w_751\",\"w_736,w_737,w_751\",0],[\"\\u51fa\\u6765\",\"w_752\",\"\",0]],\"www.keke.com\",\"29\"]]","tag":["鸽子","鸽派人物"]}}