{"trans_result":{"phonetic":[{"src_str":"内","trg_str":"nèi"},{"src_str":"疚","trg_str":"jiù"},{"src_str":"的","trg_str":"de"}],"data":[{"result":[[0,"内疚的",["0|6"],[],["0|6"],["0|9"]]],"prefixWrap":0,"dst":"内疚的","src":"guilty"}],"from":"en","to":"zh","type":2,"status":0},"dict_result":{"oxford":{"entry":[{"data":[{"data":[{"p":"adj","p_text":"adj.","tag":"p"},{"data":[{"data":[{"data":[{"data":[{"chText":"","enText":"guiltier","tag":"if"},{"chText":"","enText":"guiltiest","tag":"if"}],"tag":"info"}],"tag":"alone"}],"tag":"if-g"}],"tag":"ifs-g"},{"data":[{"text":" More guilty and most guilty are more common.","hoverText":""},{"tag":"chn","text":"more guilty和most guilty更常见。"}],"tag":"help"},{"data":[{"texts":["~ (about sth)"],"tag":"cf"},{"chText":"感到内疚的；感到惭愧的","enText":"feeling ashamed because you have done sth that you know is wrong or have not done sth that you should have done","tag":"d"},{"chText":"我因没有常去看望父母而感到内疚。","enText":"I felt guilty about not visiting my parents more often.","tag":"x"},{"chText":"约翰脸上显出惭愧的表情。","enText":"John had a guilty look on his face.","tag":"x"},{"chText":"我问心有愧，睡不着觉。","enText":"I had a guilty conscience and could not sleep.","tag":"x"}],"tag":"n-g","n":"1"},{"data":[{"texts":["~ (of sth)"],"tag":"cf"},{"chText":"犯了罪；有过失的；有罪责的","enText":"having done sth illegal; being responsible for sth bad that has happened","tag":"d"},{"chText":"陪审团裁决被告无罪。","enText":"The jury found the defendant not guilty of the offence.","tag":"x"},{"chText":"他承认犯有谋杀罪。","enText":"He pleaded guilty to murder.","tag":"x"},{"chText":"有罪的一方当事人","enText":" the guilty party (= the person responsible for sth bad happening) ","tag":"x"},{"chText":"我们每个人一生中都有过自私自利的过失。","enText":"We've all been guilty of selfishness at some time in our lives.","tag":"x"},{"data":[{"data":[{"canTrans":"1","text":"innocent","hoverText":""}],"tag":"xr"}],"tag":"xrs","xt":"opp"}],"tag":"n-g","n":"2"},{"data":[{"data":[{"canTrans":"1","text":"guiltily"}],"tag":"dr"},{"p":"adv","p_text":"adv.","tag":"p"}],"tag":"dr-g"},{"data":[{"data":[{"chText":"","enText":"a guilty secret","tag":"id"},{"chText":"见不得人的秘密","enText":"a secret that sb feels ashamed about","tag":"d"}],"tag":"id-g"}],"tag":"ids-g"}],"tag":"h-g"}],"name":"guilty","tag":"entry"}],"unbox":""},"simple_means":{"word_means":["内疚的","感到惭愧的","犯了罪","有过失的"],"from":"original","exchange":{"word_est":["guiltiest"],"word_er":["guiltier"]},"derivative":[{"data":[{"data":[{"canTrans":"1","text":"guiltily"}],"tag":"dr"},{"p":"adv","p_text":"adv.","tag":"p"}],"tag":"dr-g"}],"word_name":"guilty","symbols":[{"ph_other":"","parts":[{"means":["内疚的","感到惭愧的","犯了罪","有过失的"],"part":"adj."}],"ph_am":"ˈɡɪlti","ph_en":"ˈɡɪlti"}],"tags":{"core":["高考","CET4","考研","IELTS"],"other":["TEM4","TEM8","GRE"]}},"usecase":{"collocation":{"data":[{"p":"v.","ex":[{"en":"feel guilty","zh":"感到内疚的"},{"en":"look guilty","zh":"看上去内疚的"},{"en":"find someone guilty","zh":"认定某人有罪（或有过失）的"},{"en":"plead (not) guilty","zh":"（不）承认有罪（或有过失）的"},{"en":"prove someone guilty","zh":"证明某人有罪（或有过失）的"}]},{"p":"n.","ex":[{"en":"guilty conscience","zh":"负罪感"},{"en":"guilty secret","zh":"罪恶的秘密"},{"en":"guilty party","zh":"有罪的一方；过错方"},{"en":"guilty plea","zh":"认罪；认错"},{"en":"guilty verdict","zh":"有罪（或有过错）的裁定"}]},{"p":"prep.","ex":[{"en":"guilty of something","zh":"有…罪行（或过错）的"}]}],"desc":"guilty与以下词性连用"},"idiom":[{"p":"adj.","data":[{"data":[{"chText":"","enText":"a guilty secret","tag":"id"},{"chText":"见不得人的秘密","enText":"a secret that sb feels ashamed about","tag":"d"}],"tag":"id-g"}],"tag":"ids-g"}]},"edict":{"item":[{"tr_group":[{"similar_word":["hangdog","shamefaced","shamed"],"tr":["showing a sense of guilt"],"example":["a guilty look","the hangdog and shamefaced air of the retreating enemy\"- Eric Linklate"]},{"similar_word":[],"tr":["responsible for or chargeable with a reprehensible act"],"example":["guilty of murder","the guilty person","secret guilty deeds"]}],"pos":"adj"}],"word":"guilty"},"collins":{"entry":[{"type":"mean","entry_id":"32354","value":[{"def":"If you feel <b>guilty</b>, you feel unhappy because you think that you have done something wrong or have failed to do something which you should have done.","mean_type":[{"info_type":"example","info_id":"42300","example":[{"tts_mp3":"a/3/7/a370157a68f77c054aee51b39da2ec40.mp3","ex":"I feel so guilty, leaving all this to you...","tts_size":"15.0","example_id":"40526","tran":"把这些事都留给你去做，我真感到过意不去。"}]},{"info_type":"example","info_id":"42301","example":[{"tts_mp3":"1/b/6/1b6d6b4988c7c96b06b8336f6634b594.mp3","ex":"When she saw me she looked guilty.","tts_size":"9.0","example_id":"40527","tran":"她见到我时一脸歉疚。"}]}],"posp":[{"label":"ADJ-GRADED"}],"gramarinfo":[{"label":"usu v-link ADJ, oft ADJ <l>about</l> n","type":"hdgr","tran":""}],"tran":"内疚的；感到愧疚的","mean_id":"30961"}]},{"type":"rnon","entry_id":"32355","value":[{"rnon_id":"1955","mean":[{"def":"","mean_type":[{"info_type":"example","info_id":"42302","example":[{"tts_mp3":"7/2/c/72c7afe891500086ad663b414eada367.mp3","ex":"He glanced guiltily over his shoulder.","example_id":"40528","tran":"他很内疚地回头一瞥。"}]}],"posp":[],"gramarinfo":[],"tran":"","mean_id":"30962"}],"head_word":"guiltily"}]},{"type":"mean","entry_id":"32356","value":[{"def":"<b>Guilty</b> is used of an action or fact that you feel guilty about.","mean_type":[{"info_type":"example","info_id":"42303","example":[{"tts_mp3":"2/9/b/29b2b61eb34e74ab9742ea490de7c969.mp3","ex":"Many may be keeping it a guilty secret...","tts_size":"11.0","example_id":"40529","tran":"许多人或许保守着这个罪恶的秘密。"}]},{"info_type":"example","info_id":"42304","example":[{"tts_mp3":"f/1/5/f1589e63b475d7cb9d25d3b07c3ae258.mp3","ex":"I leave with a guilty sense of relief.","tts_size":"11.0","example_id":"40530","tran":"我带着一种罪恶的解脱感离开。"}]},{"info_type":"xrse","xrse":[{"def":"<b>guilty conscience</b>","xrse_id":"915","posc":[],"xrse_see":"conscience","defx":[]}],"info_id":"42305"}],"posp":[{"label":"ADJ"}],"gramarinfo":[{"label":"ADJ n","type":"hdgr","tran":""}],"tran":"罪恶的","mean_id":"30963"}]},{"type":"mean","entry_id":"32357","value":[{"def":"If someone is <b>guilty of</b> a crime or offence, they have committed that crime or offence.","mean_type":[{"info_type":"example","info_id":"42306","example":[{"tts_mp3":"2/5/3/253188ca38061754329845df3ad20e26.mp3","ex":"They were found guilty of murder...","tts_size":"10.0","example_id":"40531","tran":"他们被判谋杀罪成立。"}]},{"info_type":"example","info_id":"42307","example":[{"tts_mp3":"1/a/7/1a7088ea9bf58b4df40bbe4dd120aaa5.mp3","ex":"He pleaded guilty to causing actual bodily harm.","tts_size":"15.0","example_id":"40532","tran":"他承认确实犯有人身伤害罪。"}]}],"posp":[{"label":"ADJ"}],"gramarinfo":[{"label":"oft ADJ <l>of</l> n/-ing","type":"hdgr","tran":""}],"tran":"犯罪的；有罪的","mean_id":"30964"}]},{"type":"mean","entry_id":"32358","value":[{"def":"If someone is <b>guilty of</b> doing something wrong, they have done that thing.","mean_type":[{"info_type":"example","info_id":"42308","example":[{"tts_mp3":"f/7/0/f703dc7b44fd62965f2f7fe2c641e8aa.mp3","ex":"He claimed Mr Brooke had been guilty of a 'gross error of judgment'...","tts_size":"17.0","example_id":"40533","tran":"他宣称布鲁克先生犯有“判断失误的重大过错”。"}]},{"info_type":"example","info_id":"42309","example":[{"tts_mp3":"c/3/a/c3aa4b4bc0b501b57d48b732754c8fea.mp3","ex":"They will consider whether or not he has been guilty of serious professional misconduct.","tts_size":"23.0","example_id":"40534","tran":"他们将考虑他是否犯有玩忽职守的重大过失。"}]}],"posp":[{"label":"ADJ"}],"gramarinfo":[{"label":"oft ADJ <l>of</l> n/-ing","type":"hdgr","tran":""}],"tran":"有过失的","mean_id":"30965"}]}],"word_emphasize":"guilty","word_id":"14810","word_name":"guilty","frequence":"3"},"baidu_phrase":[{"tit":["Guilty Gear"],"trans":["罪恶装备；圣骑士之战；罪恶工具；罪恶克星；格斗圣骑士产"]},{"tit":["plead guilty"],"trans":["认罪；服罪；被检控的罪名；认罪服法从而减轻处罚制度；认罪的"]},{"tit":["Innocently Guilty"],"trans":["法内有情天"]},{"tit":["guilty intent"],"trans":["犯罪动机，犯罪意图"]},{"tit":["The Guilty"],"trans":["法网杀机；全面失控"]},{"tit":["guilty feeling"],"trans":["罪恶感；愧疚心理；罪咎感；愧疚感；负罪感"]},{"tit":["guilty person"],"trans":["罪人"]},{"tit":["declare guilty"],"trans":["判罪"]},{"tit":["guilty of"],"trans":["犯罪；有罪"]},{"tit":["plead guilty"],"trans":["认罪；服罪；被检控的罪名；认罪服法从而减轻处罚制度；认罪的"]},{"tit":["feel guilty"],"trans":["感到内疚的"]},{"tit":["feel guilty about"],"trans":["感到愧疚"]},{"tit":["guilty conscience"],"trans":["负罪感"]},{"tit":["be found guilty"],"trans":["被判有罪"]},{"tit":["guilty party"],"trans":["有罪的一方；过错方"]},{"tit":["guilty feeling"],"trans":["罪恶感；愧疚心理；罪咎感；愧疚感；负罪感"]}],"from":"original","lang":"1","queryExplainVideo":{"plays":"0","user_name":"智课网","videoType":"8","query":"guilty","duplicate_id":"0","created_at":"2021-01-18 14:45:07","reject_reason":"","type":"0","search_type":"1","coverUrl":"http://media8.smartstudy.com/images/3000ci/guilty.jpg","user_pic":"https://fanyiapp.cdn.bcebos.com/cms/oldimage/9358d109b3de9c824de830d66381800a18d843de.jpg","updated_at":"2021-01-18 14:45:08","videoUrl":"http://media6.smartstudy.com/7c/44/67844/5/dest.mp4?hmsr=25","user_id":"986547206","feed_url":"http://media8.smartstudy.com/images/3000ci/guilty.jpg","id":3878,"tag":"讲解","detail":"guilty的视频讲解","videoTime":"34","thumbUrl":"https://fanyiapp.cdn.bcebos.com/ugc/image/zhike_guilty.jpg","direction":"en_zh","status":"0","likes":"268"}},"logid":1052636902,"liju_result":{"single":"[[[[\"Eder\",\"w_0\",0,\" \"],[\"was\",\"w_1\",0,\" \"],[\"also\",\"w_2\",0,\" \"],[\"found\",\"w_3\",0,\" \"],[\"guilty\",\"w_4\",0,\" \"],[\"of\",\"w_5\",0,\" \"],[\"\\\"\",\"w_6\",0],[\"using\",\"w_7\",0,\" \"],[\"a\",\"w_8\",0,\" \"],[\"prohibited\",\"w_9\",0,\" \"],[\"method\",\"w_10\",0],[\"\\\"\",\"w_11\",0],[\".\",\"w_12\",0]],\"http:\\/\\/www.chinadaily.com.cn\\/cndy\\/2008-01\\/09\\/content_6380091.htm\"],[[[\"If\",\"w_13\",0,\" \"],[\"found\",\"w_14\",0,\" \"],[\"guilty\",\"w_15\",0],[\",\",\"w_16\",0,\" \"],[\"she\",\"w_17\",0,\" \"],[\"would\",\"w_18\",0,\" \"],[\"be\",\"w_19\",0,\" \"],[\"thrown\",\"w_20\",0,\" \"],[\"out\",\"w_21\",0,\" \"],[\"of\",\"w_22\",0,\" \"],[\"the\",\"w_23\",0,\" \"],[\"games\",\"w_24\",0],[\".\",\"w_25\",0]],\"http:\\/\\/www.chinadaily.com.cn\\/english\\/doc\\/2006-02\\/16\\/content_520991.htm\"],[[[\"All\",\"w_26\",0,\" \"],[\"the\",\"w_27\",0,\" \"],[\"defendants\",\"w_28\",0,\" \"],[\"pleaded\",\"w_29\",0,\" \"],[\"guilty\",\"w_30\",0,\" \"],[\"to\",\"w_31\",0,\" \"],[\"the\",\"w_32\",0,\" \"],[\"charges\",\"w_33\",0],[\",\",\"w_34\",0,\" \"],[\"said\",\"w_35\",0,\" \"],[\"the\",\"w_36\",0,\" \"],[\"statement\",\"w_37\",0],[\".\",\"w_38\",0]],\"http:\\/\\/www.chinadaily.com.cn\\/china\\/2010-03\\/31\\/content_9671332.htm\"],[[[\"Bastien\",\"w_39\",0,\" \"],[\"pleaded\",\"w_40\",0,\" \"],[\"guilty\",\"w_41\",0,\" \"],[\"to\",\"w_42\",0,\" \"],[\"conspiracy\",\"w_43\",0,\" \"],[\"to\",\"w_44\",0,\" \"],[\"commit\",\"w_45\",0,\" \"],[\"murder\",\"w_46\",0,\" \"],[\"in\",\"w_47\",0,\" \"],[\"James\",\"w_48\",0],[\"'\",\"w_49\",0,\" \"],[\"death\",\"w_50\",0],[\".\",\"w_51\",0]],\"http:\\/\\/www.chinadaily.com.cn\\/world\\/2008-11\\/20\\/content_7223890.htm\"],[[[\"DNA\",\"w_52\",0,\" \"],[\"tests\",\"w_53\",0,\" \"],[\"revealed\",\"w_54\",0,\" \"],[\"that\",\"w_55\",0,\" \"],[\"he\",\"w_56\",0,\" \"],[\"was\",\"w_57\",0,\" \"],[\"guilty\",\"w_58\",0,\" \"],[\"of\",\"w_59\",0,\" \"],[\"Katerina\",\"w_60\",0],[\"'s\",\"w_61\",0,\" \"],[\"killing\",\"w_62\",0,\" \"],[\"too\",\"w_63\",0],[\".\",\"w_64\",0]],\"http:\\/\\/www.chinadaily.com.cn\\/english\\/doc\\/2004-04\\/05\\/content_320704.htm\"],[[[\"Or\",\"w_65\",0,\" \"],[\"they\",\"w_66\",0,\" \"],[\"may\",\"w_67\",0,\" \"],[\"feel\",\"w_68\",0,\" \"],[\"guilty\",\"w_69\",0],[\",\",\"w_70\",0,\" \"],[\"like\",\"w_71\",0,\" \"],[\"they\",\"w_72\",0,\" \"],[\"have\",\"w_73\",0,\" \"],[\"done\",\"w_74\",0,\" \"],[\"something\",\"w_75\",0,\" \"],[\"wrong\",\"w_76\",0],[\".\",\"w_77\",0]],\"http:\\/\\/www.chinadaily.com.cn\\/language_tips\\/2006-12\\/06\\/content_751579.htm\"],[[[\"If\",\"w_78\",0,\" \"],[\"Gatlin\",\"w_79\",0,\" \"],[\"is\",\"w_80\",0,\" \"],[\"proven\",\"w_81\",0,\" \"],[\"guilty\",\"w_82\",0],[\",\",\"w_83\",0,\" \"],[\"his\",\"w_84\",0,\" \"],[\"world\",\"w_85\",0,\" \"],[\"record\",\"w_86\",0,\" \"],[\"would\",\"w_87\",0,\" \"],[\"be\",\"w_88\",0,\" \"],[\"stripped\",\"w_89\",0],[\".\",\"w_90\",0]],\"http:\\/\\/www.chinadaily.com.cn\\/sports\\/2006-07\\/31\\/content_653542.htm\"],[[[\"Chin\",\"w_91\",0,\" \"],[\"had\",\"w_92\",0,\" \"],[\"been\",\"w_93\",0,\" \"],[\"found\",\"w_94\",0,\" \"],[\"guilty\",\"w_95\",0,\" \"],[\"of\",\"w_96\",0,\" \"],[\"the\",\"w_97\",0,\" \"],[\"two\",\"w_98\",0,\" \"],[\"counts\",\"w_99\",0,\" \"],[\"on\",\"w_100\",0,\" \"],[\"September\",\"w_101\",0,\" \"],[\"25\",\"w_102\",0],[\".\",\"w_103\",0]],\"http:\\/\\/www.chinadaily.com.cn\\/hkedition\\/2009-10\\/16\\/content_8800740.htm\"],[[[\"In\",\"w_104\",0,\" \"],[\"all\",\"w_105\",0],[\",\",\"w_106\",0,\" \"],[\"16\",\"w_107\",0,\" \"],[\"people\",\"w_108\",0,\" \"],[\"were\",\"w_109\",0,\" \"],[\"found\",\"w_110\",0,\" \"],[\"guilty\",\"w_111\",0,\" \"],[\"and\",\"w_112\",0,\" \"],[\"eight\",\"w_113\",0,\" \"],[\"were\",\"w_114\",0,\" \"],[\"cleared\",\"w_115\",0],[\".\",\"w_116\",0]],\"http:\\/\\/www.chinadaily.com.cn\\/sports\\/2011-11\\/10\\/content_14090451.htm\"],[[[\"Before\",\"w_117\",0,\" \"],[\"that\",\"w_118\",0],[\",\",\"w_119\",0,\" \"],[\"his\",\"w_120\",0,\" \"],[\"three\",\"w_121\",0,\" \"],[\"predecessors\",\"w_122\",0,\" \"],[\"had\",\"w_123\",0,\" \"],[\"been\",\"w_124\",0,\" \"],[\"found\",\"w_125\",0,\" \"],[\"guilty\",\"w_126\",0,\" \"],[\"of\",\"w_127\",0,\" \"],[\"corruption\",\"w_128\",0],[\".\",\"w_129\",0]],\"http:\\/\\/www.chinadaily.com.cn\\/china\\/2011-01\\/07\\/content_11806525.htm\"],[[[\"No\",\"w_130\",0,\" \"],[\"contest\",\"w_131\",0,\" \"],[\"is\",\"w_132\",0,\" \"],[\"the\",\"w_133\",0,\" \"],[\"equivalent\",\"w_134\",0,\" \"],[\"of\",\"w_135\",0,\" \"],[\"a\",\"w_136\",0,\" \"],[\"guilty\",\"w_137\",0,\" \"],[\"plea\",\"w_138\",0,\" \"],[\"under\",\"w_139\",0,\" \"],[\"California\",\"w_140\",0,\" \"],[\"law\",\"w_141\",0],[\".\",\"w_142\",0]],\"http:\\/\\/www.chinadaily.com.cn\\/entertainment\\/2007-08\\/03\\/content_6010861.htm\"],[[[\"Li\",\"w_143\",0,\" \"],[\"has\",\"w_144\",0,\" \"],[\"said\",\"w_145\",0,\" \"],[\"he\",\"w_146\",0,\" \"],[\"is\",\"w_147\",0,\" \"],[\"not\",\"w_148\",0,\" \"],[\"guilty\",\"w_149\",0,\" \"],[\"of\",\"w_150\",0,\" \"],[\"the\",\"w_151\",0,\" \"],[\"accusations\",\"w_152\",0,\" \"],[\"against\",\"w_153\",0,\" \"],[\"him\",\"w_154\",0],[\".\",\"w_155\",0]],\"http:\\/\\/www.chinadaily.com.cn\\/cndy\\/2009-12\\/19\\/content_9201912.htm\"],[[[\"He\",\"w_156\",0,\" \"],[\"should\",\"w_157\",0,\" \"],[\"be\",\"w_158\",0,\" \"],[\"left\",\"w_159\",0,\" \"],[\"in\",\"w_160\",0,\" \"],[\"peace\",\"w_161\",0,\" \"],[\"if\",\"w_162\",0,\" \"],[\"he\",\"w_163\",0,\" \"],[\"is\",\"w_164\",0,\" \"],[\"not\",\"w_165\",0,\" \"],[\"found\",\"w_166\",0,\" \"],[\"guilty\",\"w_167\",0],[\".\",\"w_168\",0]],\"http:\\/\\/www.chinadaily.com.cn\\/sports\\/2008-02\\/19\\/content_6465954.htm\"],[[[\"The\",\"w_169\",0,\" \"],[\"Shapingba\",\"w_170\",0,\" \"],[\"district\",\"w_171\",0,\" \"],[\"court\",\"w_172\",0,\" \"],[\"found\",\"w_173\",0,\" \"],[\"the\",\"w_174\",0,\" \"],[\"accused\",\"w_175\",0,\" \"],[\"guilty\",\"w_176\",0,\" \"],[\"of\",\"w_177\",0,\" \"],[\"credit\",\"w_178\",0,\" \"],[\"card\",\"w_179\",0,\" \"],[\"fraud\",\"w_180\",0],[\".\",\"w_181\",0]],\"http:\\/\\/www.chinadaily.com.cn\\/cndy\\/2010-10\\/14\\/content_11407633.htm\"],[[[\"Stewart\",\"w_182\",0,\" \"],[\"also\",\"w_183\",0,\" \"],[\"was\",\"w_184\",0,\" \"],[\"found\",\"w_185\",0,\" \"],[\"guilty\",\"w_186\",0,\" \"],[\"on\",\"w_187\",0,\" \"],[\"all\",\"w_188\",0,\" \"],[\"charges\",\"w_189\",0,\" \"],[\"and\",\"w_190\",0,\" \"],[\"taken\",\"w_191\",0,\" \"],[\"into\",\"w_192\",0,\" \"],[\"custody\",\"w_193\",0],[\".\",\"w_194\",0]],\"http:\\/\\/www.chinadaily.com.cn\\/world\\/2008-10\\/04\\/content_7076759.htm\"],[[[\"Gong\",\"w_195\",0,\" \"],[\"pleaded\",\"w_196\",0,\" \"],[\"guilty\",\"w_197\",0,\" \"],[\"at\",\"w_198\",0,\" \"],[\"the\",\"w_199\",0,\" \"],[\"court\",\"w_200\",0,\" \"],[\"and\",\"w_201\",0,\" \"],[\"said\",\"w_202\",0,\" \"],[\"he\",\"w_203\",0,\" \"],[\"would\",\"w_204\",0,\" \"],[\"not\",\"w_205\",0,\" \"],[\"appeal\",\"w_206\",0],[\".\",\"w_207\",0]],\"http:\\/\\/www.chinadaily.com.cn\\/china\\/2006-07\\/14\\/content_641129.htm\"],[[[\"She\",\"w_208\",0,\" \"],[\"pleaded\",\"w_209\",0,\" \"],[\"not\",\"w_210\",0,\" \"],[\"guilty\",\"w_211\",0,\" \"],[\"in\",\"w_212\",0,\" \"],[\"February\",\"w_213\",0,\" \"],[\"to\",\"w_214\",0,\" \"],[\"misdemeanor\",\"w_215\",0,\" \"],[\"driving\",\"w_216\",0,\" \"],[\"under\",\"w_217\",0,\" \"],[\"the\",\"w_218\",0,\" \"],[\"influence\",\"w_219\",0],[\".\",\"w_220\",0]],\"http:\\/\\/www.chinadaily.com.cn\\/entertainment\\/2007-07\\/11\\/content_5432640.htm\"],[[[\"In\",\"w_221\",0,\" \"],[\"court\",\"w_222\",0],[\",\",\"w_223\",0,\" \"],[\"the\",\"w_224\",0,\" \"],[\"three\",\"w_225\",0,\" \"],[\"were\",\"w_226\",0,\" \"],[\"found\",\"w_227\",0,\" \"],[\"guilty\",\"w_228\",0,\" \"],[\"of\",\"w_229\",0,\" \"],[\"damaging\",\"w_230\",0,\" \"],[\"computer\",\"w_231\",0,\" \"],[\"systems\",\"w_232\",0],[\".\",\"w_233\",0]],\"http:\\/\\/www.chinadaily.com.cn\\/english\\/doc\\/2005-11\\/15\\/content_494599.htm\"],[[[\"Mr\",\"w_234\",0,\" \"],[\"Miller\",\"w_235\",0,\" \"],[\"was\",\"w_236\",0,\" \"],[\"not\",\"w_237\",0,\" \"],[\"in\",\"w_238\",0,\" \"],[\"court\",\"w_239\",0,\" \"],[\"when\",\"w_240\",0,\" \"],[\"the\",\"w_241\",0,\" \"],[\"guilty\",\"w_242\",0,\" \"],[\"verdict\",\"w_243\",0,\" \"],[\"was\",\"w_244\",0,\" \"],[\"announced\",\"w_245\",0],[\".\",\"w_246\",0]],\"http:\\/\\/www.chinadaily.com.cn\\/language_tips\\/2007-06\\/07\\/content_888942.htm\"],[[[\"He\",\"w_247\",0,\" \"],[\"was\",\"w_248\",0,\" \"],[\"subsequently\",\"w_249\",0,\" \"],[\"found\",\"w_250\",0,\" \"],[\"guilty\",\"w_251\",0,\" \"],[\"and\",\"w_252\",0,\" \"],[\"sentenced\",\"w_253\",0,\" \"],[\"to\",\"w_254\",0,\" \"],[\"three\",\"w_255\",0,\" \"],[\"years\",\"w_256\",0],[\"'\",\"w_257\",0,\" \"],[\"imprisonment\",\"w_258\",0],[\".\",\"w_259\",0]],\"http:\\/\\/www.chinadaily.com.cn\\/english\\/doc\\/2004-12\\/23\\/content_402816.htm\"],[[[\"Ivanovic\",\"w_260\",0,\" \"],[\"faces\",\"w_261\",0,\" \"],[\"a\",\"w_262\",0,\" \"],[\"suspension\",\"w_263\",0,\" \"],[\"if\",\"w_264\",0,\" \"],[\"he\",\"w_265\",0,\" \"],[\"is\",\"w_266\",0,\" \"],[\"found\",\"w_267\",0,\" \"],[\"guilty\",\"w_268\",0,\" \"],[\"by\",\"w_269\",0,\" \"],[\"the\",\"w_270\",0,\" \"],[\"FA\",\"w_271\",0],[\".\",\"w_272\",0]],\"http:\\/\\/www.chinadaily.com.cn\\/cndy\\/2012-04\\/12\\/content_15027746.htm\"],[[[\"He\",\"w_273\",0,\" \"],[\"has\",\"w_274\",0,\" \"],[\"pleaded\",\"w_275\",0,\" \"],[\"not\",\"w_276\",0,\" \"],[\"guilty\",\"w_277\",0,\" \"],[\"to\",\"w_278\",0,\" \"],[\"eight\",\"w_279\",0,\" \"],[\"murder\",\"w_280\",0,\" \"],[\"charges\",\"w_281\",0,\" \"],[\"and\",\"w_282\",0,\" \"],[\"other\",\"w_283\",0,\" \"],[\"crimes\",\"w_284\",0],[\".\",\"w_285\",0]],\"http:\\/\\/www.chinadaily.com.cn\\/world\\/2008-08\\/23\\/content_6964601.htm\"],[[[\"The\",\"w_286\",0,\" \"],[\"defendant\",\"w_287\",0,\" \"],[\"pleaded\",\"w_288\",0,\" \"],[\"guilty\",\"w_289\",0,\" \"],[\"on\",\"w_290\",0,\" \"],[\"three\",\"w_291\",0,\" \"],[\"of\",\"w_292\",0,\" \"],[\"them\",\"w_293\",0,\" \"],[\"while\",\"w_294\",0,\" \"],[\"denying\",\"w_295\",0,\" \"],[\"the\",\"w_296\",0,\" \"],[\"rest\",\"w_297\",0],[\".\",\"w_298\",0]],\"http:\\/\\/www.chinadaily.com.cn\\/hkedition\\/2008-03\\/01\\/content_6498157.htm\"],[[[\"The\",\"w_299\",0,\" \"],[\"punishment\",\"w_300\",0,\" \"],[\"also\",\"w_301\",0,\" \"],[\"applies\",\"w_302\",0,\" \"],[\"to\",\"w_303\",0,\" \"],[\"leaders\",\"w_304\",0,\" \"],[\"found\",\"w_305\",0,\" \"],[\"guilty\",\"w_306\",0,\" \"],[\"of\",\"w_307\",0,\" \"],[\"dereliction\",\"w_308\",0,\" \"],[\"of\",\"w_309\",0,\" \"],[\"duty\",\"w_310\",0],[\".\",\"w_311\",0]],\"http:\\/\\/www.chinadaily.com.cn\\/bizchina\\/2008-09\\/11\\/content_7021294.htm\"],[[[\"All\",\"w_312\",0,\" \"],[\"four\",\"w_313\",0,\" \"],[\"had\",\"w_314\",0,\" \"],[\"earlier\",\"w_315\",0,\" \"],[\"pleaded\",\"w_316\",0,\" \"],[\"not\",\"w_317\",0,\" \"],[\"guilty\",\"w_318\",0,\" \"],[\"and\",\"w_319\",0,\" \"],[\"will\",\"w_320\",0,\" \"],[\"appeal\",\"w_321\",0,\" \"],[\"the\",\"w_322\",0,\" \"],[\"verdict\",\"w_323\",0],[\".\",\"w_324\",0]],\"http:\\/\\/www.chinadaily.com.cn\\/cndy\\/2009-06\\/17\\/content_8291225.htm\"],[[[\"But\",\"w_325\",0,\" \"],[\"I\",\"w_326\",0,\" \"],[\"felt\",\"w_327\",0,\" \"],[\"guilty\",\"w_328\",0,\" \"],[\"as\",\"w_329\",0,\" \"],[\"if\",\"w_330\",0,\" \"],[\"we\",\"w_331\",0,\" \"],[\"Chinese\",\"w_332\",0,\" \"],[\"were\",\"w_333\",0,\" \"],[\"eating\",\"w_334\",0,\" \"],[\"panda\",\"w_335\",0,\" \"],[\"meat\",\"w_336\",0],[\".\",\"w_337\",0]],\"http:\\/\\/www.chinadaily.com.cn\\/cndy\\/2011-04\\/25\\/content_12384200.htm\"],[[[\"He\",\"w_338\",0,\" \"],[\"did\",\"w_339\",0,\" \"],[\"not\",\"w_340\",0,\" \"],[\"specify\",\"w_341\",0,\" \"],[\"the\",\"w_342\",0,\" \"],[\"charges\",\"w_343\",0,\" \"],[\"to\",\"w_344\",0,\" \"],[\"which\",\"w_345\",0,\" \"],[\"he\",\"w_346\",0,\" \"],[\"will\",\"w_347\",0,\" \"],[\"plead\",\"w_348\",0,\" \"],[\"guilty\",\"w_349\",0],[\".\",\"w_350\",0]],\"http:\\/\\/www.chinadaily.com.cn\\/english\\/doc\\/2004-08\\/24\\/content_368126.htm\"],[[[\"Franco\",\"w_351\",0],[\",\",\"w_352\",0,\" \"],[\"who\",\"w_353\",0,\" \"],[\"has\",\"w_354\",0,\" \"],[\"pleaded\",\"w_355\",0,\" \"],[\"not\",\"w_356\",0,\" \"],[\"guilty\",\"w_357\",0,\" \"],[\"to\",\"w_358\",0,\" \"],[\"burglary\",\"w_359\",0,\" \"],[\"and\",\"w_360\",0,\" \"],[\"stalking\",\"w_361\",0,\" \"],[\"charges\",\"w_362\",0],[\".\",\"w_363\",0]],\"http:\\/\\/www.chinadaily.com.cn\\/entertainment\\/2011-10\\/18\\/content_13923956.htm\"],[[[\"Lam\",\"w_364\",0,\" \"],[\"earlier\",\"w_365\",0,\" \"],[\"pleaded\",\"w_366\",0,\" \"],[\"guilty\",\"w_367\",0,\" \"],[\"to\",\"w_368\",0,\" \"],[\"one\",\"w_369\",0,\" \"],[\"count\",\"w_370\",0,\" \"],[\"of\",\"w_371\",0,\" \"],[\"dangerous\",\"w_372\",0,\" \"],[\"driving\",\"w_373\",0,\" \"],[\"causing\",\"w_374\",0,\" \"],[\"death\",\"w_375\",0],[\".\",\"w_376\",0]],\"http:\\/\\/www.chinadaily.com.cn\\/hkedition\\/2012-11\\/24\\/content_15955110.htm\"],[[[\"The\",\"w_377\",0,\" \"],[\"court\",\"w_378\",0,\" \"],[\"said\",\"w_379\",0,\" \"],[\"Zhang\",\"w_380\",0,\" \"],[\"was\",\"w_381\",0,\" \"],[\"guilty\",\"w_382\",0,\" \"],[\"of\",\"w_383\",0,\" \"],[\"the\",\"w_384\",0,\" \"],[\"crime\",\"w_385\",0,\" \"],[\"of\",\"w_386\",0,\" \"],[\"negligent\",\"w_387\",0,\" \"],[\"homicide\",\"w_388\",0],[\".\",\"w_389\",0]],\"http:\\/\\/www.chinadaily.com.cn\\/cndy\\/2010-10\\/19\\/content_11426715.htm\"]]","double":"[[[[\"His\",\"w_0\",\"w_0,w_7\",0,\" \"],[\"guilty\",\"w_1\",\"w_1,w_8\",1,\" \"],[\"expression\",\"w_2\",\"w_2,w_10\",0,\" \"],[\"confirmed\",\"w_3\",\"w_3,w_11\",0,\" \"],[\"my\",\"w_4\",\"w_4,w_13\",0,\" \"],[\"suspicions\",\"w_5\",\"w_5,w_15\",0],[\".\",\"w_6\",\"w_6,w_16\",0]],[[\"\\u4ed6\",\"w_7\",\"w_0,w_7\",0],[\"\\u5185\\u759a\",\"w_8\",\"w_1,w_8\",0],[\"\\u7684\",\"w_9\",\"\",0],[\"\\u8868\\u60c5\",\"w_10\",\"w_2,w_10\",0],[\"\\u8bc1\\u5b9e\",\"w_11\",\"w_3,w_11\",0],[\"\\u4e86\",\"w_12\",\"\",0],[\"\\u6211\",\"w_13\",\"w_4,w_13\",0],[\"\\u7684\",\"w_14\",\"\",0],[\"\\u731c\\u7591\",\"w_15\",\"w_5,w_15\",0],[\"\\u3002\",\"w_16\",\"w_6,w_16\",0]],\"\\u300a\\u725b\\u6d25\\u9ad8\\u9636\\u82f1\\u6c49\\u53cc\\u89e3\\u8bcd\\u5178\\u300b\",\"0\"],[[[\"All\",\"w_17\",\"w_17,w_31\",0,\" \"],[\"I\",\"w_18\",\"w_18,w_19,w_37\",0],[\"'m\",\"w_19\",\"w_18,w_19,w_37\",0,\" \"],[\"guilty\",\"w_20\",\"w_20,w_35\",1,\" \"],[\"of\",\"w_21\",\"w_21,w_36\",0,\" \"],[\"is\",\"w_22\",\"w_22,w_43\",0,\" \"],[\"trying\",\"w_23\",\"w_23,w_24,w_44\",0,\" \"],[\"to\",\"w_24\",\"w_23,w_24,w_44\",0,\" \"],[\"make\",\"w_25\",\"w_25,w_45\",0,\" \"],[\"his\",\"w_26\",\"w_26,w_46\",0,\" \"],[\"life\",\"w_27\",\"w_27,w_47\",0,\" \"],[\"easier\",\"w_28\",\"w_28,w_48,w_49,w_50\",0],[\".\",\"w_29\",\"w_29,w_51\",0],[\"-\",\"w_30\",\"w_30\",0]],[[\"guilty:\",\"w_31\",\"w_17,w_31\",0],[\"\\u6709\\u7f6a\",\"w_32\",\"\",0],[\"\\u7684\",\"w_33\",\"\",0],[\"\\uff0c\",\"w_34\",\"\",0],[\"\\u5185\\u759a\",\"w_35\",\"w_20,w_35\",0],[\"\\u7684\",\"w_36\",\"w_21,w_36\",0],[\"\\u6211\",\"w_37\",\"w_18,w_19,w_37\",0],[\"\\u6240\",\"w_38\",\"\",0],[\"\\u505a\",\"w_39\",\"\",0],[\"\\u7684\",\"w_40\",\"\",0],[\"\\u4e00\\u5207\",\"w_41\",\"\",0],[\"\\u90fd\",\"w_42\",\"\",0],[\"\\u662f\",\"w_43\",\"w_22,w_43\",0],[\"\\u4e3a\\u4e86\",\"w_44\",\"w_23,w_24,w_44\",0],[\"\\u8ba9\",\"w_45\",\"w_25,w_45\",0],[\"\\u4ed6\",\"w_46\",\"w_26,w_46\",0],[\"\\u6d3b\",\"w_47\",\"w_27,w_47\",0],[\"\\u5f97\",\"w_48\",\"w_28,w_48,w_49,w_50\",0],[\"\\u66f4\",\"w_49\",\"w_28,w_48,w_49,w_50\",0],[\"\\u8f7b\\u677e\",\"w_50\",\"w_28,w_48,w_49,w_50\",0],[\"\\u3002\",\"w_51\",\"w_29,w_51\",0]],\"www.keke.com\",\"1\"],[[[\"He\",\"w_52\",\"w_52,w_62\",0,\" \"],[\"was\",\"w_53\",\"w_53,w_63\",0,\" \"],[\"brought\",\"w_54\",\"w_54,w_55,w_64\",0,\" \"],[\"before\",\"w_55\",\"w_54,w_55,w_64\",0,\" \"],[\"the\",\"w_56\",\"w_56,w_67\",0,\" \"],[\"court\",\"w_57\",\"w_57,w_65\",0,\" \"],[\"and\",\"w_58\",\"w_58,w_68\",0,\" \"],[\"found\",\"w_59\",\"w_59,w_60,w_69,w_70,w_71\",0,\" \"],[\"guilty\",\"w_60\",\"w_59,w_60,w_69,w_70,w_71\",1],[\".\",\"w_61\",\"w_61,w_72\",0]],[[\"\\u4ed6\",\"w_62\",\"w_52,w_62\",0],[\"\\u88ab\",\"w_63\",\"w_53,w_63\",0],[\"\\u9001\\u4ea4\",\"w_64\",\"w_54,w_55,w_64\",0],[\"\\u6cd5\\u5ead\",\"w_65\",\"w_57,w_65\",0],[\"\\u5ba1\\u5224\",\"w_66\",\"\",0],[\"\\uff0c\",\"w_67\",\"w_56,w_67\",0],[\"\\u5e76\",\"w_68\",\"w_58,w_68\",0],[\"\\u88ab\",\"w_69\",\"w_59,w_60,w_69,w_70,w_71\",0],[\"\\u88c1\\u5b9a\",\"w_70\",\"w_59,w_60,w_69,w_70,w_71\",0],[\"\\u6709\\u7f6a\",\"w_71\",\"w_59,w_60,w_69,w_70,w_71\",0],[\"\\u3002\",\"w_72\",\"w_61,w_72\",0]],\"\\u300a\\u725b\\u6d25\\u9ad8\\u9636\\u82f1\\u6c49\\u53cc\\u89e3\\u8bcd\\u5178\\u300b\",\"2\"],[[[\"He\",\"w_73\",\"w_73,w_83\",0,\" \"],[\"was\",\"w_74\",\"w_74,w_84\",0,\" \"],[\"found\",\"w_75\",\"w_75,w_76,w_85,w_86\",0,\" \"],[\"guilty\",\"w_76\",\"w_75,w_76,w_85,w_86\",1,\" \"],[\"and\",\"w_77\",\"w_77,w_87\",0,\" \"],[\"given\",\"w_78\",\"w_78,w_88\",0,\" \"],[\"a\",\"w_79\",\"w_79,w_90\",0,\" \"],[\"conditional\",\"w_80\",\"w_80,w_91,w_92\",0,\" \"],[\"discharge\",\"w_81\",\"w_81,w_93\",0],[\".\",\"w_82\",\"w_82,w_94\",0]],[[\"\\u4ed6\",\"w_83\",\"w_73,w_83\",0],[\"\\u88ab\",\"w_84\",\"w_74,w_84\",0],[\"\\u5224\\u5b9a\",\"w_85\",\"w_75,w_76,w_85,w_86\",0],[\"\\u6709\\u7f6a\",\"w_86\",\"w_75,w_76,w_85,w_86\",0],[\"\\u5e76\",\"w_87\",\"w_77,w_87\",0],[\"\\u88ab\",\"w_88\",\"w_78,w_88\",0],[\"\\u5224\\u5904\",\"w_89\",\"\",0],[\"\\u6709\",\"w_90\",\"w_79,w_90\",0],[\"\\u6761\\u4ef6\",\"w_91\",\"w_80,w_91,w_92\",0],[\"\\u7684\",\"w_92\",\"w_80,w_91,w_92\",0],[\"\\u91ca\\u653e\",\"w_93\",\"w_81,w_93\",0],[\"\\u3002\",\"w_94\",\"w_82,w_94\",0]],\"\\u300a\\u725b\\u6d25\\u9ad8\\u9636\\u82f1\\u6c49\\u53cc\\u89e3\\u8bcd\\u5178\\u300b\",\"3\"],[[[\"In\",\"w_95\",\"w_95,w_106\",0,\" \"],[\"this\",\"w_96\",\"w_96,w_107\",0,\" \"],[\"country\",\"w_97\",\"w_97,w_108\",0],[\",\",\"w_98\",\"w_98,w_109\",0,\" \"],[\"you\",\"w_99\",\"w_99,w_112\",0,\" \"],[\"are\",\"w_100\",\"w_100,w_113\",0,\" \"],[\"innocent\",\"w_101\",\"w_101,w_119\",0,\" \"],[\"until\",\"w_102\",\"w_102,w_116\",0,\" \"],[\"proved\",\"w_103\",\"w_103,w_114\",0,\" \"],[\"guilty\",\"w_104\",\"w_104,w_115\",1],[\".\",\"w_105\",\"w_105,w_121\",0]],[[\"\\u5728\",\"w_106\",\"w_95,w_106\",0],[\"\\u8fd9\\u4e2a\",\"w_107\",\"w_96,w_107\",0],[\"\\u56fd\\u5bb6\",\"w_108\",\"w_97,w_108\",0],[\"\\uff0c\",\"w_109\",\"w_98,w_109\",0],[\"\\u4e00\",\"w_110\",\"\",0],[\"\\u4e2a\\u4eba\",\"w_111\",\"\",0],[\"\\u5728\",\"w_112\",\"w_99,w_112\",0],[\"\\u88ab\",\"w_113\",\"w_100,w_113\",0],[\"\\u8bc1\\u5b9e\",\"w_114\",\"w_103,w_114\",0],[\"\\u6709\\u7f6a\",\"w_115\",\"w_104,w_115\",0],[\"\\u4e4b\\u524d\",\"w_116\",\"w_102,w_116\",0],[\"\\uff0c\",\"w_117\",\"\",0],[\"\\u5c31\\u662f\",\"w_118\",\"\",0],[\"\\u6e05\\u767d\",\"w_119\",\"w_101,w_119\",0],[\"\\u7684\",\"w_120\",\"\",0],[\"\\u3002\",\"w_121\",\"w_105,w_121\",0]],\"\\u300a\\u725b\\u6d25\\u9ad8\\u9636\\u82f1\\u6c49\\u53cc\\u89e3\\u8bcd\\u5178\\u300b\",\"4\"],[[[\"They\",\"w_122\",\"w_122,w_133\",0,\" \"],[\"were\",\"w_123\",\"w_123,w_134\",0,\" \"],[\"found\",\"w_124\",\"w_124,w_125,w_126,w_127,w_128,w_137,w_138,w_139,w_140\",0,\" \"],[\"guilty\",\"w_125\",\"w_124,w_125,w_126,w_127,w_128,w_137,w_138,w_139,w_140\",1,\" \"],[\"of\",\"w_126\",\"w_124,w_125,w_126,w_127,w_128,w_137,w_138,w_139,w_140\",0,\" \"],[\"causing\",\"w_127\",\"w_124,w_125,w_126,w_127,w_128,w_137,w_138,w_139,w_140\",0,\" \"],[\"unnecessary\",\"w_128\",\"w_124,w_125,w_126,w_127,w_128,w_137,w_138,w_139,w_140\",0,\" \"],[\"suffering\",\"w_129\",\"w_129\",0,\" \"],[\"to\",\"w_130\",\"w_130\",0,\" \"],[\"animals\",\"w_131\",\"w_131,w_136\",0],[\".\",\"w_132\",\"w_132,w_141\",0]],[[\"\\u4ed6\\u4eec\",\"w_133\",\"w_122,w_133\",0],[\"\\u56e0\",\"w_134\",\"w_123,w_134\",0],[\"\\u8650\\u5f85\",\"w_135\",\"\",0],[\"\\u52a8\\u7269\",\"w_136\",\"w_131,w_136\",0],[\"\\u800c\",\"w_137\",\"w_124,w_125,w_126,w_127,w_128,w_137,w_138,w_139,w_140\",0],[\"\\u88ab\",\"w_138\",\"w_124,w_125,w_126,w_127,w_128,w_137,w_138,w_139,w_140\",0],[\"\\u5224\",\"w_139\",\"w_124,w_125,w_126,w_127,w_128,w_137,w_138,w_139,w_140\",0],[\"\\u6709\\u7f6a\",\"w_140\",\"w_124,w_125,w_126,w_127,w_128,w_137,w_138,w_139,w_140\",0],[\"\\u3002\",\"w_141\",\"w_132,w_141\",0]],\"\\u300a\\u725b\\u6d25\\u9ad8\\u9636\\u82f1\\u6c49\\u53cc\\u89e3\\u8bcd\\u5178\\u300b\",\"5\"],[[[\"The\",\"w_142\",\"w_142,w_157\",0,\" \"],[\"prevailing\",\"w_143\",\"w_143,w_155,w_156\",0,\" \"],[\"view\",\"w_144\",\"w_144,w_158\",0,\" \"],[\"seems\",\"w_145\",\"w_145,w_146,w_147,w_159\",0,\" \"],[\"to\",\"w_146\",\"w_145,w_146,w_147,w_159\",0,\" \"],[\"be\",\"w_147\",\"w_145,w_146,w_147,w_159\",0,\" \"],[\"that\",\"w_148\",\"w_148,w_160\",0,\" \"],[\"they\",\"w_149\",\"w_149,w_150,w_162\",0,\" \"],[\"will\",\"w_150\",\"w_149,w_150,w_162\",0,\" \"],[\"find\",\"w_151\",\"w_151,w_163\",0,\" \"],[\"her\",\"w_152\",\"w_152,w_161\",0,\" \"],[\"guilty\",\"w_153\",\"w_153,w_164,w_165\",1],[\".\",\"w_154\",\"w_154,w_166\",0]],[[\"\\u4e00\\u822c\",\"w_155\",\"w_143,w_155,w_156\",0],[\"\\u4eba\",\"w_156\",\"w_143,w_155,w_156\",0],[\"\\u7684\",\"w_157\",\"w_142,w_157\",0],[\"\\u770b\\u6cd5\",\"w_158\",\"w_144,w_158\",0],[\"\\u4f3c\\u4e4e\",\"w_159\",\"w_145,w_146,w_147,w_159\",0],[\"\\u8ba4\\u4e3a\",\"w_160\",\"w_148,w_160\",0],[\"\\u5979\",\"w_161\",\"w_152,w_161\",0],[\"\\u4f1a\",\"w_162\",\"w_149,w_150,w_162\",0],[\"\\u88ab\",\"w_163\",\"w_151,w_163\",0],[\"\\u5224\",\"w_164\",\"w_153,w_164,w_165\",0],[\"\\u6709\\u7f6a\",\"w_165\",\"w_153,w_164,w_165\",0],[\"\\u3002\",\"w_166\",\"w_154,w_166\",0]],\"\\u300a\\u725b\\u6d25\\u9ad8\\u9636\\u82f1\\u6c49\\u53cc\\u89e3\\u8bcd\\u5178\\u300b\",\"6\"],[[[\"It\",\"w_167\",\"w_167,w_185\",0,\" \"],[\"took\",\"w_168\",\"w_168,w_169,w_183,w_184\",0,\" \"],[\"the\",\"w_169\",\"w_168,w_169,w_183,w_184\",0,\" \"],[\"jury\",\"w_170\",\"w_170,w_182\",0,\" \"],[\"some\",\"w_171\",\"w_171\",0,\" \"],[\"time\",\"w_172\",\"w_172,w_186,w_187\",0,\" \"],[\"to\",\"w_173\",\"w_173,w_188\",0,\" \"],[\"reach\",\"w_174\",\"w_174,w_175,w_189\",0,\" \"],[\"the\",\"w_175\",\"w_174,w_175,w_189\",0,\" \"],[\"conclusion\",\"w_176\",\"w_176,w_190\",0,\" \"],[\"that\",\"w_177\",\"w_177,w_191\",0,\" \"],[\"she\",\"w_178\",\"w_178,w_192\",0,\" \"],[\"was\",\"w_179\",\"w_179\",0,\" \"],[\"guilty\",\"w_180\",\"w_180,w_193\",1],[\".\",\"w_181\",\"w_181,w_194\",0]],[[\"\\u966a\\u5ba1\",\"w_182\",\"w_170,w_182\",0],[\"\\u56e2\\u82b1\",\"w_183\",\"w_168,w_169,w_183,w_184\",0],[\"\\u4e86\",\"w_184\",\"w_168,w_169,w_183,w_184\",0],[\"\\u5f88\",\"w_185\",\"w_167,w_185\",0],[\"\\u957f\",\"w_186\",\"w_172,w_186,w_187\",0],[\"\\u65f6\\u95f4\",\"w_187\",\"w_172,w_186,w_187\",0],[\"\\u624d\",\"w_188\",\"w_173,w_188\",0],[\"\\u5f97\\u51fa\",\"w_189\",\"w_174,w_175,w_189\",0],[\"\\u7ed3\\u8bba\",\"w_190\",\"w_176,w_190\",0],[\"\\u8ba4\\u4e3a\",\"w_191\",\"w_177,w_191\",0],[\"\\u5979\",\"w_192\",\"w_178,w_192\",0],[\"\\u6709\\u7f6a\",\"w_193\",\"w_180,w_193\",0],[\"\\u3002\",\"w_194\",\"w_181,w_194\",0]],\"\\u300a\\u725b\\u6d25\\u9ad8\\u9636\\u82f1\\u6c49\\u53cc\\u89e3\\u8bcd\\u5178\\u300b\",\"7\"],[[[\"In\",\"w_195\",\"w_195,w_209\",0,\" \"],[\"English\",\"w_196\",\"w_196,w_210\",0,\" \"],[\"law\",\"w_197\",\"w_197,w_211\",0,\" \"],[\"a\",\"w_198\",\"w_198,w_212,w_213\",0,\" \"],[\"person\",\"w_199\",\"w_199,w_214\",0,\" \"],[\"is\",\"w_200\",\"w_200,w_215\",0,\" \"],[\"accounted\",\"w_201\",\"w_201,w_216\",0,\" \"],[\"innocent\",\"w_202\",\"w_202\",0,\" \"],[\"until\",\"w_203\",\"w_203,w_219\",0,\" \"],[\"they\",\"w_204\",\"w_204,w_205,w_220,w_221,w_222\",0,\" \"],[\"are\",\"w_205\",\"w_204,w_205,w_220,w_221,w_222\",0,\" \"],[\"proved\",\"w_206\",\"w_206,w_217\",0,\" \"],[\"guilty\",\"w_207\",\"w_207,w_218\",1],[\".\",\"w_208\",\"w_208,w_224\",0]],[[\"\\u6309\",\"w_209\",\"w_195,w_209\",0],[\"\\u82f1\\u683c\\u5170\",\"w_210\",\"w_196,w_210\",0],[\"\\u6cd5\\u5f8b\",\"w_211\",\"w_197,w_211\",0],[\"\\uff0c\",\"w_212\",\"w_198,w_212,w_213\",0],[\"\\u4e00\",\"w_213\",\"w_198,w_212,w_213\",0],[\"\\u4e2a\\u4eba\",\"w_214\",\"w_199,w_214\",0],[\"\\u672a\",\"w_215\",\"w_200,w_215\",0],[\"\\u7ecf\",\"w_216\",\"w_201,w_216\",0],[\"\\u8bc1\\u5b9e\",\"w_217\",\"w_206,w_217\",0],[\"\\u6709\\u7f6a\",\"w_218\",\"w_207,w_218\",0],[\"\\u4e4b\\u524d\",\"w_219\",\"w_203,w_219\",0],[\"\\u88ab\",\"w_220\",\"w_204,w_205,w_220,w_221,w_222\",0],[\"\\u89c6\",\"w_221\",\"w_204,w_205,w_220,w_221,w_222\",0],[\"\\u4e3a\",\"w_222\",\"w_204,w_205,w_220,w_221,w_222\",0],[\"\\u65e0\\u7f6a\",\"w_223\",\"\",0],[\"\\u3002\",\"w_224\",\"w_208,w_224\",0]],\"\\u300a\\u725b\\u6d25\\u9ad8\\u9636\\u82f1\\u6c49\\u53cc\\u89e3\\u8bcd\\u5178\\u300b\",\"8\"],[[[\"He\",\"w_225\",\"w_225,w_244\",0,\" \"],[\"was\",\"w_226\",\"w_226\",0,\" \"],[\"found\",\"w_227\",\"w_227,w_246\",0,\" \"],[\"not\",\"w_228\",\"w_228,w_229,w_247\",0,\" \"],[\"guilty\",\"w_229\",\"w_228,w_229,w_247\",1,\" \"],[\"because\",\"w_230\",\"w_230,w_238\",0,\" \"],[\"of\",\"w_231\",\"w_231,w_243\",0,\" \"],[\"holes\",\"w_232\",\"w_232\",0,\" \"],[\"in\",\"w_233\",\"w_233,w_245\",0,\" \"],[\"the\",\"w_234\",\"w_234\",0,\" \"],[\"prosecution\",\"w_235\",\"w_235,w_239\",0,\" \"],[\"case\",\"w_236\",\"w_236,w_240\",0],[\".\",\"w_237\",\"w_237,w_248\",0]],[[\"\\u7531\\u4e8e\",\"w_238\",\"w_230,w_238\",0],[\"\\u8d77\\u8bc9\",\"w_239\",\"w_235,w_239\",0],[\"\\u6848\\u60c5\",\"w_240\",\"w_236,w_240\",0],[\"\\u6709\",\"w_241\",\"\",0],[\"\\u7834\\u7efd\",\"w_242\",\"\",0],[\"\\uff0c\",\"w_243\",\"w_231,w_243\",0],[\"\\u4ed6\",\"w_244\",\"w_225,w_244\",0],[\"\\u88ab\",\"w_245\",\"w_233,w_245\",0],[\"\\u5224\",\"w_246\",\"w_227,w_246\",0],[\"\\u65e0\\u7f6a\",\"w_247\",\"w_228,w_229,w_247\",0],[\"\\u3002\",\"w_248\",\"w_237,w_248\",0]],\"\\u300a\\u725b\\u6d25\\u9ad8\\u9636\\u82f1\\u6c49\\u53cc\\u89e3\\u8bcd\\u5178\\u300b\",\"9\"],[[[\"In\",\"w_249\",\"w_249,w_266\",0,\" \"],[\"English\",\"w_250\",\"w_250,w_262\",0,\" \"],[\"law\",\"w_251\",\"w_251,w_263,w_264\",0],[\",\",\"w_252\",\"w_252,w_265\",0,\" \"],[\"a\",\"w_253\",\"w_253,w_268\",0,\" \"],[\"person\",\"w_254\",\"w_254,w_269\",0,\" \"],[\"is\",\"w_255\",\"w_255,w_274\",0,\" \"],[\"presumed\",\"w_256\",\"w_256,w_275\",0,\" \"],[\"innocent\",\"w_257\",\"w_257,w_276\",0,\" \"],[\"until\",\"w_258\",\"w_258,w_271\",0,\" \"],[\"proved\",\"w_259\",\"w_259,w_267\",0,\" \"],[\"guilty\",\"w_260\",\"w_260,w_270\",1],[\".\",\"w_261\",\"w_261,w_277\",0]],[[\"\\u82f1\\u56fd\",\"w_262\",\"w_250,w_262\",0],[\"\\u6cd5\\u5f8b\",\"w_263\",\"w_251,w_263,w_264\",0],[\"\\u89c4\\u5b9a\",\"w_264\",\"w_251,w_263,w_264\",0],[\"\\uff0c\",\"w_265\",\"w_252,w_265\",0],[\"\\u5728\",\"w_266\",\"w_249,w_266\",0],[\"\\u8bc1\\u660e\",\"w_267\",\"w_259,w_267\",0],[\"\\u4e00\",\"w_268\",\"w_253,w_268\",0],[\"\\u4e2a\\u4eba\",\"w_269\",\"w_254,w_269\",0],[\"\\u6709\\u7f6a\",\"w_270\",\"w_260,w_270\",0],[\"\\u4e4b\\u524d\",\"w_271\",\"w_258,w_271\",0],[\"\\uff0c\",\"w_272\",\"\",0],[\"\\u4ed6\",\"w_273\",\"\",0],[\"\\u662f\",\"w_274\",\"w_255,w_274\",0],[\"\\u63a8\\u5b9a\",\"w_275\",\"w_256,w_275\",0],[\"\\u65e0\\u8f9c\",\"w_276\",\"w_257,w_276\",0],[\"\\u3002\",\"w_277\",\"w_261,w_277\",0]],\"\\u300a\\u725b\\u6d25\\u9ad8\\u9636\\u82f1\\u6c49\\u53cc\\u89e3\\u8bcd\\u5178\\u300b\",\"10\"],[[[\"He\",\"w_278\",\"w_278,w_289\",0,\" \"],[\"was\",\"w_279\",\"w_279,w_290\",0,\" \"],[\"found\",\"w_280\",\"w_280,w_296\",0,\" \"],[\"not\",\"w_281\",\"w_281\",0,\" \"],[\"guilty\",\"w_282\",\"w_282\",1],[\",\",\"w_283\",\"w_283\",0,\" \"],[\"by\",\"w_284\",\"w_284,w_295\",0,\" \"],[\"reason\",\"w_285\",\"w_285,w_294\",0,\" \"],[\"of\",\"w_286\",\"w_286\",0,\" \"],[\"insanity\",\"w_287\",\"w_287,w_297\",0],[\".\",\"w_288\",\"w_288,w_298\",0]],[[\"\\u4ed6\",\"w_289\",\"w_278,w_289\",0],[\"\\u4ee5\",\"w_290\",\"w_279,w_290\",0],[\"\\u7cbe\\u795e\",\"w_291\",\"\",0],[\"\\u5931\\u5e38\",\"w_292\",\"\",0],[\"\\u4e3a\",\"w_293\",\"\",0],[\"\\u7406\\u7531\",\"w_294\",\"w_285,w_294\",0],[\"\\u83b7\",\"w_295\",\"w_284,w_295\",0],[\"\\u5224\",\"w_296\",\"w_280,w_296\",0],[\"\\u65e0\\u7f6a\",\"w_297\",\"w_287,w_297\",0],[\"\\u3002\",\"w_298\",\"w_288,w_298\",0]],\"\\u300a\\u725b\\u6d25\\u9ad8\\u9636\\u82f1\\u6c49\\u53cc\\u89e3\\u8bcd\\u5178\\u300b\",\"11\"],[[[\"The\",\"w_299\",\"w_299\",0,\" \"],[\"company\",\"w_300\",\"w_300,w_311\",0,\" \"],[\"was\",\"w_301\",\"w_301,w_309,w_310\",0,\" \"],[\"found\",\"w_302\",\"w_302,w_303,w_313\",0,\" \"],[\"guilty\",\"w_303\",\"w_302,w_303,w_313\",1,\" \"],[\"of\",\"w_304\",\"w_304,w_305,w_314,w_315\",0,\" \"],[\"contravening\",\"w_305\",\"w_304,w_305,w_314,w_315\",0,\" \"],[\"safety\",\"w_306\",\"w_306,w_316\",0,\" \"],[\"regulations\",\"w_307\",\"w_307,w_317\",0],[\".\",\"w_308\",\"w_308,w_318\",0]],[[\"\\u90a3\",\"w_309\",\"w_301,w_309,w_310\",0],[\"\\u5bb6\",\"w_310\",\"w_301,w_309,w_310\",0],[\"\\u516c\\u53f8\",\"w_311\",\"w_300,w_311\",0],[\"\\u88ab\",\"w_312\",\"\",0],[\"\\u5224\",\"w_313\",\"w_302,w_303,w_313\",0],[\"\\u8fdd\\u53cd\",\"w_314\",\"w_304,w_305,w_314,w_315\",0],[\"\\u4e86\",\"w_315\",\"w_304,w_305,w_314,w_315\",0],[\"\\u5b89\\u5168\",\"w_316\",\"w_306,w_316\",0],[\"\\u6761\\u4f8b\",\"w_317\",\"w_307,w_317\",0],[\"\\u3002\",\"w_318\",\"w_308,w_318\",0]],\"\\u300a\\u725b\\u6d25\\u9ad8\\u9636\\u82f1\\u6c49\\u53cc\\u89e3\\u8bcd\\u5178\\u300b\",\"12\"],[[[\"He\",\"w_319\",\"w_319\",0,\" \"],[\"said\",\"w_320\",\"w_320,w_344\",0,\" \"],[\"he\",\"w_321\",\"w_321,w_336\",0,\" \"],[\"would\",\"w_322\",\"w_322,w_345\",0,\" \"],[\"appeal\",\"w_323\",\"w_323,w_346\",0,\" \"],[\"after\",\"w_324\",\"w_324\",0,\" \"],[\"being\",\"w_325\",\"w_325\",0,\" \"],[\"found\",\"w_326\",\"w_326,w_327,w_337\",0,\" \"],[\"guilty\",\"w_327\",\"w_326,w_327,w_337\",1,\" \"],[\"on\",\"w_328\",\"w_328\",0,\" \"],[\"four\",\"w_329\",\"w_329,w_338\",0,\" \"],[\"counts\",\"w_330\",\"w_330,w_339\",0,\" \"],[\"of\",\"w_331\",\"w_331\",0,\" \"],[\"murder\",\"w_332\",\"w_332,w_340\",0],[\".\",\"w_333\",\"w_333,w_347\",0]],[[\"\\u6cd5\\u5ead\",\"w_334\",\"\",0],[\"\\u5224\\u51b3\",\"w_335\",\"\",0],[\"\\u4ed6\",\"w_336\",\"w_321,w_336\",0],[\"\\u72af\\u6709\",\"w_337\",\"w_326,w_327,w_337\",0],[\"\\u56db\",\"w_338\",\"w_329,w_338\",0],[\"\\u9879\",\"w_339\",\"w_330,w_339\",0],[\"\\u8c0b\\u6740\",\"w_340\",\"w_332,w_340\",0],[\"\\u7f6a\",\"w_341\",\"\",0],[\"\\uff0c\",\"w_342\",\"\",0],[\"\\u4ed6\",\"w_343\",\"\",0],[\"\\u8868\\u793a\",\"w_344\",\"w_320,w_344\",0],[\"\\u8981\",\"w_345\",\"w_322,w_345\",0],[\"\\u4e0a\\u8bc9\",\"w_346\",\"w_323,w_346\",0],[\"\\u3002\",\"w_347\",\"w_333,w_347\",0]],\"\\u300a\\u725b\\u6d25\\u9ad8\\u9636\\u82f1\\u6c49\\u53cc\\u89e3\\u8bcd\\u5178\\u300b\",\"13\"],[[[\"He\",\"w_348\",\"w_348,w_357\",0,\" \"],[\"was\",\"w_349\",\"w_349,w_358\",0,\" \"],[\"found\",\"w_350\",\"w_350,w_359\",0,\" \"],[\"guilty\",\"w_351\",\"w_351,w_352,w_360\",1,\" \"],[\"of\",\"w_352\",\"w_351,w_352,w_360\",0,\" \"],[\"handling\",\"w_353\",\"w_353,w_354,w_355,w_361\",0,\" \"],[\"stolen\",\"w_354\",\"w_353,w_354,w_355,w_361\",0,\" \"],[\"goods\",\"w_355\",\"w_353,w_354,w_355,w_361\",0],[\".\",\"w_356\",\"w_356,w_363\",0]],[[\"\\u4ed6\",\"w_357\",\"w_348,w_357\",0],[\"\\u88ab\",\"w_358\",\"w_349,w_358\",0],[\"\\u5224\",\"w_359\",\"w_350,w_359\",0],[\"\\u72af\",\"w_360\",\"w_351,w_352,w_360\",0],[\"\\u9500\\u8d43\",\"w_361\",\"w_353,w_354,w_355,w_361\",0],[\"\\u7f6a\",\"w_362\",\"\",0],[\"\\u3002\",\"w_363\",\"w_356,w_363\",0]],\"\\u300a\\u725b\\u6d25\\u9ad8\\u9636\\u82f1\\u6c49\\u53cc\\u89e3\\u8bcd\\u5178\\u300b\",\"14\"],[[[\"The\",\"w_364\",\"w_364\",0,\" \"],[\"police\",\"w_365\",\"w_365,w_366,w_377\",0,\" \"],[\"officers\",\"w_366\",\"w_365,w_366,w_377\",0,\" \"],[\"were\",\"w_367\",\"w_367,w_376\",0,\" \"],[\"found\",\"w_368\",\"w_368,w_369,w_370,w_379,w_380\",0,\" \"],[\"guilty\",\"w_369\",\"w_368,w_369,w_370,w_379,w_380\",1,\" \"],[\"of\",\"w_370\",\"w_368,w_369,w_370,w_379,w_380\",0,\" \"],[\"serious\",\"w_371\",\"w_371,w_381\",0,\" \"],[\"dereliction\",\"w_372\",\"w_372,w_373,w_374,w_382,w_383\",0,\" \"],[\"of\",\"w_373\",\"w_372,w_373,w_374,w_382,w_383\",0,\" \"],[\"duty\",\"w_374\",\"w_372,w_373,w_374,w_382,w_383\",0],[\".\",\"w_375\",\"w_375,w_384\",0]],[[\"\\u8fd9\\u4e9b\",\"w_376\",\"w_367,w_376\",0],[\"\\u8b66\\u5bdf\",\"w_377\",\"w_365,w_366,w_377\",0],[\"\\u88ab\",\"w_378\",\"\",0],[\"\\u5224\",\"w_379\",\"w_368,w_369,w_370,w_379,w_380\",0],[\"\\u72af\\u6709\",\"w_380\",\"w_368,w_369,w_370,w_379,w_380\",0],[\"\\u4e25\\u91cd\",\"w_381\",\"w_371,w_381\",0],[\"\\u6e0e\\u804c\",\"w_382\",\"w_372,w_373,w_374,w_382,w_383\",0],[\"\\u7f6a\",\"w_383\",\"w_372,w_373,w_374,w_382,w_383\",0],[\"\\u3002\",\"w_384\",\"w_375,w_384\",0]],\"\\u300a\\u725b\\u6d25\\u9ad8\\u9636\\u82f1\\u6c49\\u53cc\\u89e3\\u8bcd\\u5178\\u300b\",\"15\"],[[[\"Implicit\",\"w_385\",\"w_385\",0,\" \"],[\"in\",\"w_386\",\"w_386,w_399\",0,\" \"],[\"his\",\"w_387\",\"w_387,w_397\",0,\" \"],[\"speech\",\"w_388\",\"w_388,w_398\",0,\" \"],[\"was\",\"w_389\",\"w_389,w_402\",0,\" \"],[\"the\",\"w_390\",\"w_390,w_391,w_400,w_401\",0,\" \"],[\"assumption\",\"w_391\",\"w_390,w_391,w_400,w_401\",0,\" \"],[\"that\",\"w_392\",\"w_392,w_403\",0,\" \"],[\"they\",\"w_393\",\"w_393,w_404\",0,\" \"],[\"were\",\"w_394\",\"w_394\",0,\" \"],[\"guilty\",\"w_395\",\"w_395,w_405\",1],[\".\",\"w_396\",\"w_396,w_406\",0]],[[\"\\u4ed6\",\"w_397\",\"w_387,w_397\",0],[\"\\u8bdd\\u8bed\",\"w_398\",\"w_388,w_398\",0],[\"\\u4e2d\",\"w_399\",\"w_386,w_399\",0],[\"\\u7684\",\"w_400\",\"w_390,w_391,w_400,w_401\",0],[\"\\u8a00\\u5916\\u4e4b\\u610f\",\"w_401\",\"w_390,w_391,w_400,w_401\",0],[\"\\u662f\",\"w_402\",\"w_389,w_402\",0],[\"\\u8bbe\\u5b9a\",\"w_403\",\"w_392,w_403\",0],[\"\\u4ed6\\u4eec\",\"w_404\",\"w_393,w_404\",0],[\"\\u6709\\u7f6a\",\"w_405\",\"w_395,w_405\",0],[\"\\u3002\",\"w_406\",\"w_396,w_406\",0]],\"\\u300a\\u725b\\u6d25\\u9ad8\\u9636\\u82f1\\u6c49\\u53cc\\u89e3\\u8bcd\\u5178\\u300b\",\"16\"],[[[\"The\",\"w_407\",\"w_407,w_419\",0,\" \"],[\"jury\",\"w_408\",\"w_408,w_418\",0,\" \"],[\"deliberated\",\"w_409\",\"w_409,w_420\",0,\" \"],[\"for\",\"w_410\",\"w_410,w_421\",0,\" \"],[\"five\",\"w_411\",\"w_411,w_423\",0,\" \"],[\"days\",\"w_412\",\"w_412,w_413,w_414,w_424,w_425\",0,\" \"],[\"before\",\"w_413\",\"w_412,w_413,w_414,w_424,w_425\",0,\" \"],[\"finding\",\"w_414\",\"w_412,w_413,w_414,w_424,w_425\",0,\" \"],[\"him\",\"w_415\",\"w_415,w_426\",0,\" \"],[\"guilty\",\"w_416\",\"w_416,w_427\",1],[\".\",\"w_417\",\"w_417,w_428\",0]],[[\"\\u966a\\u5ba1\",\"w_418\",\"w_408,w_418\",0],[\"\\u56e2\",\"w_419\",\"w_407,w_419\",0],[\"\\u8ba4\\u771f\",\"w_420\",\"w_409,w_420\",0],[\"\\u8ba8\\u8bba\",\"w_421\",\"w_410,w_421\",0],[\"\\u4e86\",\"w_422\",\"\",0],[\"\\u4e94\",\"w_423\",\"w_411,w_423\",0],[\"\\u5929\\u624d\",\"w_424\",\"w_412,w_413,w_414,w_424,w_425\",0],[\"\\u88c1\\u5b9a\",\"w_425\",\"w_412,w_413,w_414,w_424,w_425\",0],[\"\\u4ed6\",\"w_426\",\"w_415,w_426\",0],[\"\\u6709\\u7f6a\",\"w_427\",\"w_416,w_427\",0],[\"\\u3002\",\"w_428\",\"w_417,w_428\",0]],\"\\u300a\\u725b\\u6d25\\u9ad8\\u9636\\u82f1\\u6c49\\u53cc\\u89e3\\u8bcd\\u5178\\u300b\",\"17\"],[[[\"He\",\"w_429\",\"w_429,w_442\",0,\" \"],[\"was\",\"w_430\",\"w_430,w_443\",0,\" \"],[\"found\",\"w_431\",\"w_431,w_432,w_433,w_444,w_445\",0,\" \"],[\"guilty\",\"w_432\",\"w_431,w_432,w_433,w_444,w_445\",1,\" \"],[\"of\",\"w_433\",\"w_431,w_432,w_433,w_444,w_445\",0,\" \"],[\"embezzling\",\"w_434\",\"w_434,w_446\",0],[\"$\",\"w_435\",\"w_435,w_447\",0,\" \"],[\"150\",\"w_436\",\"w_436,w_437,w_448,w_449\",0,\" \"],[\"000\",\"w_437\",\"w_436,w_437,w_448,w_449\",0,\" \"],[\"of\",\"w_438\",\"w_438\",0,\" \"],[\"public\",\"w_439\",\"w_439,w_450\",0,\" \"],[\"funds\",\"w_440\",\"w_440\",0],[\".\",\"w_441\",\"w_441,w_452\",0]],[[\"\\u4ed6\",\"w_442\",\"w_429,w_442\",0],[\"\\u88ab\",\"w_443\",\"w_430,w_443\",0],[\"\\u5224\",\"w_444\",\"w_431,w_432,w_433,w_444,w_445\",0],[\"\\u72af\\u6709\",\"w_445\",\"w_431,w_432,w_433,w_444,w_445\",0],[\"\\u76d7\\u7528\",\"w_446\",\"w_434,w_446\",0],[\"15\",\"w_447\",\"w_435,w_447\",0],[\"\\u4e07\",\"w_448\",\"w_436,w_437,w_448,w_449\",0],[\"\\u5143\",\"w_449\",\"w_436,w_437,w_448,w_449\",0],[\"\\u516c\\u6b3e\",\"w_450\",\"w_439,w_450\",0],[\"\\u7f6a\",\"w_451\",\"\",0],[\"\\u3002\",\"w_452\",\"w_441,w_452\",0]],\"\\u300a\\u725b\\u6d25\\u9ad8\\u9636\\u82f1\\u6c49\\u53cc\\u89e3\\u8bcd\\u5178\\u300b\",\"18\"],[[[\"They\",\"w_453\",\"w_453,w_461\",0,\" \"],[\"were\",\"w_454\",\"w_454,w_462\",0,\" \"],[\"found\",\"w_455\",\"w_455,w_456,w_463\",0,\" \"],[\"guilty\",\"w_456\",\"w_455,w_456,w_463\",1,\" \"],[\"on\",\"w_457\",\"w_457,w_458,w_464\",0,\" \"],[\"all\",\"w_458\",\"w_457,w_458,w_464\",0,\" \"],[\"counts\",\"w_459\",\"w_459,w_465\",0],[\".\",\"w_460\",\"w_460,w_467\",0]],[[\"\\u4ed6\\u4eec\",\"w_461\",\"w_453,w_461\",0],[\"\\u88ab\",\"w_462\",\"w_454,w_462\",0],[\"\\u5224\",\"w_463\",\"w_455,w_456,w_463\",0],[\"\\u5404\\u9879\",\"w_464\",\"w_457,w_458,w_464\",0],[\"\\u7f6a\\u540d\",\"w_465\",\"w_459,w_465\",0],[\"\\u6210\\u7acb\",\"w_466\",\"\",0],[\"\\u3002\",\"w_467\",\"w_460,w_467\",0]],\"\\u300a\\u725b\\u6d25\\u9ad8\\u9636\\u82f1\\u6c49\\u53cc\\u89e3\\u8bcd\\u5178\\u300b\",\"19\"],[[[\"He\",\"w_468\",\"w_468,w_478\",0,\" \"],[\"was\",\"w_469\",\"w_469,w_477\",0,\" \"],[\"found\",\"w_470\",\"w_470,w_471,w_472,w_479\",0,\" \"],[\"guilty\",\"w_471\",\"w_470,w_471,w_472,w_479\",1,\" \"],[\"of\",\"w_472\",\"w_470,w_471,w_472,w_479\",0,\" \"],[\"murder\",\"w_473\",\"w_473,w_480,w_481\",0],[\".\",\"w_474\",\"w_474,w_482\",0]],[[\"\\u7ecf\",\"w_475\",\"\",0],[\"\\u88c1\\u51b3\",\"w_476\",\"\",0],[\"\\uff0c\",\"w_477\",\"w_469,w_477\",0],[\"\\u4ed6\",\"w_478\",\"w_468,w_478\",0],[\"\\u72af\\u6709\",\"w_479\",\"w_470,w_471,w_472,w_479\",0],[\"\\u8c0b\\u6740\",\"w_480\",\"w_473,w_480,w_481\",0],[\"\\u7f6a\",\"w_481\",\"w_473,w_480,w_481\",0],[\"\\u3002\",\"w_482\",\"w_474,w_482\",0]],\"\\u300a\\u725b\\u6d25\\u9ad8\\u9636\\u82f1\\u6c49\\u53cc\\u89e3\\u8bcd\\u5178\\u300b\",\"20\"],[[[\"Assume\",\"w_483\",\"w_483,w_490\",0,\" \"],[\"A\",\"w_484\",\"w_484,w_491\",0,\" \"],[\"knows\",\"w_485\",\"w_485,w_492\",0,\" \"],[\"B\",\"w_486\",\"w_486,w_493\",0,\" \"],[\"is\",\"w_487\",\"w_487,w_494\",0,\" \"],[\"guilty\",\"w_488\",\"w_488,w_495\",1],[\".\",\"w_489\",\"w_489,w_496\",0]],[[\"\\u5047\\u5b9a\",\"w_490\",\"w_483,w_490\",0],[\"\\u7532\",\"w_491\",\"w_484,w_491\",0],[\"\\u77e5\\u9053\",\"w_492\",\"w_485,w_492\",0],[\"\\u4e59\",\"w_493\",\"w_486,w_493\",0],[\"\\u5e94\\u8d1f\",\"w_494\",\"w_487,w_494\",0],[\"\\u7f6a\\u8d23\",\"w_495\",\"w_488,w_495\",0],[\"\\u3002\",\"w_496\",\"w_489,w_496\",0]],\"\\u300a\\u725b\\u6d25\\u9ad8\\u9636\\u82f1\\u6c49\\u53cc\\u89e3\\u8bcd\\u5178\\u300b\",\"21\"],[[[\"Newspapers\",\"w_497\",\"w_497,w_506\",0,\" \"],[\"are\",\"w_498\",\"w_498,w_499,w_507\",0,\" \"],[\"often\",\"w_499\",\"w_498,w_499,w_507\",0,\" \"],[\"guilty\",\"w_500\",\"w_500,w_508\",1,\" \"],[\"of\",\"w_501\",\"w_501\",0,\" \"],[\"distorting\",\"w_502\",\"w_502,w_509\",0,\" \"],[\"the\",\"w_503\",\"w_503,w_511\",0,\" \"],[\"truth\",\"w_504\",\"w_504,w_510\",0],[\".\",\"w_505\",\"w_505,w_513\",0]],[[\"\\u62a5\\u7ae0\",\"w_506\",\"w_497,w_506\",0],[\"\\u5e38\",\"w_507\",\"w_498,w_499,w_507\",0],[\"\\u72af\",\"w_508\",\"w_500,w_508\",0],[\"\\u6b6a\\u66f2\",\"w_509\",\"w_502,w_509\",0],[\"\\u4e8b\\u5b9e\",\"w_510\",\"w_504,w_510\",0],[\"\\u7684\",\"w_511\",\"w_503,w_511\",0],[\"\\u9519\\u8bef\",\"w_512\",\"\",0],[\"\\u3002\",\"w_513\",\"w_505,w_513\",0]],\"\\u300a\\u725b\\u6d25\\u9ad8\\u9636\\u82f1\\u6c49\\u53cc\\u89e3\\u8bcd\\u5178\\u300b\",\"22\"],[[[\"If\",\"w_514\",\"w_514,w_528\",0,\" \"],[\"he\",\"w_515\",\"w_515,w_529\",0,\" \"],[\"is\",\"w_516\",\"w_516\",0,\" \"],[\"guilty\",\"w_517\",\"w_517,w_530\",1,\" \"],[\"then\",\"w_518\",\"w_518,w_532\",0],[\",\",\"w_519\",\"w_519,w_531\",0,\" \"],[\"by\",\"w_520\",\"w_520,w_533\",0,\" \"],[\"inference\",\"w_521\",\"w_521,w_535\",0],[\",\",\"w_522\",\"w_522\",0,\" \"],[\"so\",\"w_523\",\"w_523,w_534\",0,\" \"],[\"is\",\"w_524\",\"w_524\",0,\" \"],[\"his\",\"w_525\",\"w_525,w_536\",0,\" \"],[\"wife\",\"w_526\",\"w_526,w_537\",0],[\".\",\"w_527\",\"w_527,w_541\",0]],[[\"\\u5982\\u679c\",\"w_528\",\"w_514,w_528\",0],[\"\\u4ed6\",\"w_529\",\"w_515,w_529\",0],[\"\\u6709\\u7f6a\",\"w_530\",\"w_517,w_530\",0],[\"\\uff0c\",\"w_531\",\"w_519,w_531\",0],[\"\\u90a3\\u4e48\",\"w_532\",\"w_518,w_532\",0],[\"\\u7531\\u6b64\",\"w_533\",\"w_520,w_533\",0],[\"\\u53ef\\u4ee5\",\"w_534\",\"w_523,w_534\",0],[\"\\u63a8\\u65ad\",\"w_535\",\"w_521,w_535\",0],[\"\\u4ed6\\u7684\",\"w_536\",\"w_525,w_536\",0],[\"\\u59bb\\u5b50\",\"w_537\",\"w_526,w_537\",0],[\"\\u4e5f\",\"w_538\",\"\",0],[\"\\u540c\\u6837\",\"w_539\",\"\",0],[\"\\u6709\\u7f6a\",\"w_540\",\"\",0],[\"\\u3002\",\"w_541\",\"w_527,w_541\",0]],\"\\u300a\\u725b\\u6d25\\u9ad8\\u9636\\u82f1\\u6c49\\u53cc\\u89e3\\u8bcd\\u5178\\u300b\",\"23\"],[[[\"He\",\"w_542\",\"w_542,w_556\",0,\" \"],[\"was\",\"w_543\",\"w_543,w_558\",0,\" \"],[\"found\",\"w_544\",\"w_544,w_559\",0,\" \"],[\"not\",\"w_545\",\"w_545,w_557\",0,\" \"],[\"guilty\",\"w_546\",\"w_546,w_561\",1,\" \"],[\"of\",\"w_547\",\"w_547\",0,\" \"],[\"murder\",\"w_548\",\"w_548,w_560\",0,\" \"],[\"on\",\"w_549\",\"w_549,w_563,w_564\",0,\" \"],[\"the\",\"w_550\",\"w_550,w_565\",0,\" \"],[\"grounds\",\"w_551\",\"w_551,w_566\",0,\" \"],[\"of\",\"w_552\",\"w_552,w_568\",0,\" \"],[\"diminished\",\"w_553\",\"w_553,w_567\",0,\" \"],[\"responsibility\",\"w_554\",\"w_554,w_570\",0],[\".\",\"w_555\",\"w_555,w_571\",0]],[[\"\\u4ed6\",\"w_556\",\"w_542,w_556\",0],[\"\\u672a\",\"w_557\",\"w_545,w_557\",0],[\"\\u88ab\",\"w_558\",\"w_543,w_558\",0],[\"\\u5224\",\"w_559\",\"w_544,w_559\",0],[\"\\u8c0b\\u6740\",\"w_560\",\"w_548,w_560\",0],[\"\\u7f6a\",\"w_561\",\"w_546,w_561\",0],[\"\\u662f\",\"w_562\",\"\",0],[\"\\u57fa\\u4e8e\",\"w_563\",\"w_549,w_563,w_564\",0],[\"\\u7cbe\\u795e\",\"w_564\",\"w_549,w_563,w_564\",0],[\"\\u5931\\u5e38\",\"w_565\",\"w_550,w_565\",0],[\"\\u800c\",\"w_566\",\"w_551,w_566\",0],[\"\\u51cf\\u8f7b\",\"w_567\",\"w_553,w_567\",0],[\"\\u4e86\",\"w_568\",\"w_552,w_568\",0],[\"\\u5211\\u4e8b\",\"w_569\",\"\",0],[\"\\u8d23\\u4efb\",\"w_570\",\"w_554,w_570\",0],[\"\\u3002\",\"w_571\",\"w_555,w_571\",0]],\"\\u300a\\u725b\\u6d25\\u9ad8\\u9636\\u82f1\\u6c49\\u53cc\\u89e3\\u8bcd\\u5178\\u300b\",\"24\"],[[[\"He\",\"w_572\",\"w_572,w_581\",0,\" \"],[\"pleaded\",\"w_573\",\"w_573,w_574,w_588,w_589,w_590\",0,\" \"],[\"guilty\",\"w_574\",\"w_573,w_574,w_588,w_589,w_590\",1,\" \"],[\"to\",\"w_575\",\"w_575,w_585\",0,\" \"],[\"driving\",\"w_576\",\"w_576,w_586\",0,\" \"],[\"with\",\"w_577\",\"w_577,w_587\",0,\" \"],[\"excess\",\"w_578\",\"w_578,w_583\",0,\" \"],[\"alcohol\",\"w_579\",\"w_579,w_584\",0],[\".\",\"w_580\",\"w_580,w_591\",0]],[[\"\\u4ed6\",\"w_581\",\"w_572,w_581\",0],[\"\\u5bf9\",\"w_582\",\"\",0],[\"\\u8fc7\\u91cf\",\"w_583\",\"w_578,w_583\",0],[\"\\u996e\\u9152\",\"w_584\",\"w_579,w_584\",0],[\"\\u540e\",\"w_585\",\"w_575,w_585\",0],[\"\\u9a7e\\u8f66\",\"w_586\",\"w_576,w_586\",0],[\"\\u4e00\",\"w_587\",\"w_577,w_587\",0],[\"\\u4e8b\",\"w_588\",\"w_573,w_574,w_588,w_589,w_590\",0],[\"\\u8868\\u793a\",\"w_589\",\"w_573,w_574,w_588,w_589,w_590\",0],[\"\\u670d\\u7f6a\",\"w_590\",\"w_573,w_574,w_588,w_589,w_590\",0],[\"\\u3002\",\"w_591\",\"w_580,w_591\",0]],\"\\u300a\\u725b\\u6d25\\u9ad8\\u9636\\u82f1\\u6c49\\u53cc\\u89e3\\u8bcd\\u5178\\u300b\",\"25\"],[[[\"The\",\"w_592\",\"w_592,w_593,w_605\",0,\" \"],[\"judge\",\"w_593\",\"w_592,w_593,w_605\",0,\" \"],[\"directed\",\"w_594\",\"w_594,w_595,w_606\",0,\" \"],[\"the\",\"w_595\",\"w_594,w_595,w_606\",0,\" \"],[\"jury\",\"w_596\",\"w_596,w_607,w_608\",0,\" \"],[\"to\",\"w_597\",\"w_597,w_609\",0,\" \"],[\"return\",\"w_598\",\"w_598\",0,\" \"],[\"a\",\"w_599\",\"w_599\",0,\" \"],[\"verdict\",\"w_600\",\"w_600,w_611\",0,\" \"],[\"of\",\"w_601\",\"w_601\",0,\" \"],[\"not\",\"w_602\",\"w_602,w_603,w_610\",0,\" \"],[\"guilty\",\"w_603\",\"w_602,w_603,w_610\",1],[\".\",\"w_604\",\"w_604,w_612\",0]],[[\"\\u6cd5\\u5b98\",\"w_605\",\"w_592,w_593,w_605\",0],[\"\\u6307\\u793a\",\"w_606\",\"w_594,w_595,w_606\",0],[\"\\u966a\\u5ba1\",\"w_607\",\"w_596,w_607,w_608\",0],[\"\\u56e2\",\"w_608\",\"w_596,w_607,w_608\",0],[\"\\u4f5c\\u51fa\",\"w_609\",\"w_597,w_609\",0],[\"\\u65e0\\u7f6a\",\"w_610\",\"w_602,w_603,w_610\",0],[\"\\u88c1\\u51b3\",\"w_611\",\"w_600,w_611\",0],[\"\\u3002\",\"w_612\",\"w_604,w_612\",0]],\"\\u300a\\u725b\\u6d25\\u9ad8\\u9636\\u82f1\\u6c49\\u53cc\\u89e3\\u8bcd\\u5178\\u300b\",\"26\"],[[[\"The\",\"w_613\",\"w_613\",0,\" \"],[\"prosecution\",\"w_614\",\"w_614,w_628\",0,\" \"],[\"has\",\"w_615\",\"w_615,w_632\",0,\" \"],[\"to\",\"w_616\",\"w_616,w_629,w_630,w_631\",0,\" \"],[\"prove\",\"w_617\",\"w_617\",0,\" \"],[\"beyond\",\"w_618\",\"w_618\",0,\" \"],[\"reasonable\",\"w_619\",\"w_619\",0,\" \"],[\"doubt\",\"w_620\",\"w_620\",0,\" \"],[\"that\",\"w_621\",\"w_621\",0,\" \"],[\"he\",\"w_622\",\"w_622,w_633\",0,\" \"],[\"is\",\"w_623\",\"w_623\",0,\" \"],[\"guilty\",\"w_624\",\"w_624,w_634\",1,\" \"],[\"of\",\"w_625\",\"w_625,w_636\",0,\" \"],[\"murder\",\"w_626\",\"w_626,w_635\",0],[\".\",\"w_627\",\"w_627,w_637\",0]],[[\"\\u63a7\\u65b9\",\"w_628\",\"w_614,w_628\",0],[\"\\u5fc5\\u987b\",\"w_629\",\"w_616,w_629,w_630,w_631\",0],[\"\\u6beb\\u65e0\\u7591\\u4e49\",\"w_630\",\"w_616,w_629,w_630,w_631\",0],[\"\\u5730\",\"w_631\",\"w_616,w_629,w_630,w_631\",0],[\"\\u8bc1\\u660e\",\"w_632\",\"w_615,w_632\",0],[\"\\u4ed6\",\"w_633\",\"w_622,w_633\",0],[\"\\u72af\\u6709\",\"w_634\",\"w_624,w_634\",0],[\"\\u8c0b\\u6740\",\"w_635\",\"w_626,w_635\",0],[\"\\u7f6a\",\"w_636\",\"w_625,w_636\",0],[\"\\u3002\",\"w_637\",\"w_627,w_637\",0]],\"\\u300a\\u725b\\u6d25\\u9ad8\\u9636\\u82f1\\u6c49\\u53cc\\u89e3\\u8bcd\\u5178\\u300b\",\"27\"],[[[\"In\",\"w_638\",\"w_638\",0,\" \"],[\"the\",\"w_639\",\"w_639\",0,\" \"],[\"end\",\"w_640\",\"w_640,w_655\",0,\" \"],[\"the\",\"w_641\",\"w_641,w_658\",0,\" \"],[\"contrary\",\"w_642\",\"w_642,w_659\",0,\" \"],[\"was\",\"w_643\",\"w_643,w_662\",0,\" \"],[\"proved\",\"w_644\",\"w_644,w_656\",0,\" \"],[\"true\",\"w_645\",\"w_645,w_657\",0],[\":\",\"w_646\",\"w_646,w_660\",0,\" \"],[\"he\",\"w_647\",\"w_647,w_661\",0,\" \"],[\"was\",\"w_648\",\"w_648\",0,\" \"],[\"innocent\",\"w_649\",\"w_649,w_663\",0,\" \"],[\"and\",\"w_650\",\"w_650,w_666\",0,\" \"],[\"she\",\"w_651\",\"w_651,w_667\",0,\" \"],[\"was\",\"w_652\",\"w_652\",0,\" \"],[\"guilty\",\"w_653\",\"w_653,w_668,w_669\",1],[\".\",\"w_654\",\"w_654,w_670\",0]],[[\"\\u6700\\u540e\",\"w_655\",\"w_640,w_655\",0],[\"\\u8bc1\\u660e\",\"w_656\",\"w_644,w_656\",0],[\"\\u4e8b\\u5b9e\",\"w_657\",\"w_645,w_657\",0],[\"\\u6b63\\u597d\",\"w_658\",\"w_641,w_658\",0],[\"\\u76f8\\u53cd\",\"w_659\",\"w_642,w_659\",0],[\"\\uff1a\",\"w_660\",\"w_646,w_660\",0],[\"\\u4ed6\",\"w_661\",\"w_647,w_661\",0],[\"\\u662f\",\"w_662\",\"w_643,w_662\",0],[\"\\u65e0\\u8f9c\",\"w_663\",\"w_649,w_663\",0],[\"\\u7684\",\"w_664\",\"\",0],[\"\\uff0c\",\"w_665\",\"\",0],[\"\\u800c\",\"w_666\",\"w_650,w_666\",0],[\"\\u5979\",\"w_667\",\"w_651,w_667\",0],[\"\\u5219\",\"w_668\",\"w_653,w_668,w_669\",0],[\"\\u6709\\u7f6a\",\"w_669\",\"w_653,w_668,w_669\",0],[\"\\u3002\",\"w_670\",\"w_654,w_670\",0]],\"\\u300a\\u725b\\u6d25\\u9ad8\\u9636\\u82f1\\u6c49\\u53cc\\u89e3\\u8bcd\\u5178\\u300b\",\"28\"],[[[\"I\",\"w_671\",\"w_671,w_679\",0,\" \"],[\"felt\",\"w_672\",\"w_672,w_680\",0,\" \"],[\"guilty\",\"w_673\",\"w_673,w_681\",1,\" \"],[\"and\",\"w_674\",\"w_674,w_682\",0,\" \"],[\"full\",\"w_675\",\"w_675,w_683\",0,\" \"],[\"of\",\"w_676\",\"w_676\",0,\" \"],[\"remorse\",\"w_677\",\"w_677,w_685\",0],[\".\",\"w_678\",\"w_678,w_686\",0]],[[\"\\u6211\",\"w_679\",\"w_671,w_679\",0],[\"\\u611f\\u5230\",\"w_680\",\"w_672,w_680\",0],[\"\\u5185\\u759a\",\"w_681\",\"w_673,w_681\",0],[\"\\uff0c\",\"w_682\",\"w_674,w_682\",0],[\"\\u5e76\\u4e14\",\"w_683\",\"w_675,w_683\",0],[\"\\u975e\\u5e38\",\"w_684\",\"\",0],[\"\\u61ca\\u6094\",\"w_685\",\"w_677,w_685\",0],[\"\\u3002\",\"w_686\",\"w_678,w_686\",0]],\"\\u300a\\u725b\\u6d25\\u9ad8\\u9636\\u82f1\\u6c49\\u53cc\\u89e3\\u8bcd\\u5178\\u300b\",\"29\"]]","tag":["内疚的","犯了罪","有过失的"]}}